{"data": [{"lang": "en", "author_id": "11348282", "conversation_id": "1392573297762635779", "created_at": "2021-05-12T20:12:01.000Z", "id": "1392573297762635779", "public_metrics": {"retweet_count": 382, "reply_count": 96, "like_count": 2709, "quote_count": 34}, "source": "Sprinklr", "text": "Get this \ud83d\udc49 It would take ~9 weeks to transmit a complete map of Mars back to Earth with current radio frequency systems.\n\nWith lasers, it would take ~9 days\n\n\ud83d\udca5 Learn about our laser communications demo launching soon to empower future discoveries: https://t.co/5NYQ84OnBc https://t.co/KrCXl1TZ5s"}, {"lang": "en", "author_id": "11348282", "conversation_id": "1392547124794073089", "created_at": "2021-05-12T18:28:01.000Z", "id": "1392547124794073089", "public_metrics": {"retweet_count": 114, "reply_count": 36, "like_count": 1048, "quote_count": 4}, "source": "Sprinklr", "text": "\ud83d\udce1 We've long partnered with industry to provide communications and navigation services in space. In the latest \"Invisible Network\" podcast, @NASASCaN experts explain how we're bringing new commmercial companies into the market.\n\n\ud83d\udcf2 Listen &amp; subscribe: https://t.co/2a0kIBVflB https://t.co/Rs17X8Z3Gw"}, {"lang": "en", "author_id": "11348282", "conversation_id": "1392514195032350721", "created_at": "2021-05-12T16:17:10.000Z", "id": "1392514195032350721", "public_metrics": {"retweet_count": 501, "reply_count": 77, "like_count": 3351, "quote_count": 34}, "source": "Twitter Media Studio", "text": "\ud83d\udd34\u00a0\ud83d\ude81 Our Ingenuity #MarsHelicopter, but make it 3D!\n\nWhen the helicopter took to the Martian skies on its third flight, @NASAPersevere was there to capture it all. Check out the rendered flight in 3D as it ascends, hovers, then zooms laterally: https://t.co/YVY07InRKu https://t.co/dAR37lBONk"}, {"lang": "en", "author_id": "11348282", "conversation_id": "1392259489236144128", "created_at": "2021-05-11T23:25:03.000Z", "id": "1392259489236144128", "public_metrics": {"retweet_count": 901, "reply_count": 189, "like_count": 7475, "quote_count": 47}, "source": "Sprinklr", "text": "\ud83d\udc4b Goodbye, asteroid Bennu! Yesterday, our #OSIRISREx spacecraft took a final image before departing for the journey back to Earth. In 2023, it'll arrive back at our home planet, delivering a sample of rocks &amp; dust captured from the asteroid: https://t.co/Esy6uJMGu0 https://t.co/GN8CqSv7P0"}, {"lang": "en", "author_id": "11348282", "conversation_id": "1392231505041178630", "created_at": "2021-05-11T21:33:51.000Z", "id": "1392231505041178630", "public_metrics": {"retweet_count": 219, "reply_count": 71, "like_count": 1657, "quote_count": 12}, "source": "Sprinklr", "text": "During #AsianAmericanPacificIslanderHeritageMonth, we take time to recognize the amazing contributions of past and present employees of #AAPI descent. Hear from some of the resilient spirits who help power our missions every day: https://t.co/ijuQdWO7he https://t.co/6sHevzm7gH"}, {"lang": "en", "author_id": "11348282", "conversation_id": "1392201370321702912", "created_at": "2021-05-11T19:34:07.000Z", "id": "1392201370321702912", "referenced_tweets": [{"type": "retweeted", "id": "1392153779865272334"}], "public_metrics": {"retweet_count": 294, "reply_count": 0, "like_count": 0, "quote_count": 0}, "source": "Twitter Web App", "text": "RT @NASAArmstrong: The X- 57 is on its way! \u2708\ufe0f \n\nThe propellers on the X-57 Maxwell aircraft spin for the first time under electric power f\u2026"}, {"lang": "en", "author_id": "11348282", "conversation_id": "1392196813755719683", "created_at": "2021-05-11T19:16:00.000Z", "id": "1392196813755719683", "public_metrics": {"retweet_count": 1031, "reply_count": 171, "like_count": 9014, "quote_count": 52}, "source": "Sprinklr", "text": "Our @NASAPersevere Mars rover has begun studying the floor of Jezero Crater, which held a lake billions of years ago. Eventually, the rover will collect rock samples that might hold evidence of ancient microbial life: https://t.co/9g30kTbLpH https://t.co/oSHP3bC6CR"}, {"lang": "en", "author_id": "11348282", "conversation_id": "1392170711226126344", "created_at": "2021-05-11T17:32:17.000Z", "id": "1392170711226126344", "public_metrics": {"retweet_count": 707, "reply_count": 104, "like_count": 5483, "quote_count": 86}, "source": "Sprinklr", "text": "TODAY: The golden mirror on the world\u2019s largest and most powerful space telescope \u2013 @NASAWebb \u2013 opened for the last time on Earth. \n\n\u2728\ud83d\ude80 Get the details about this important milestone ahead of the mission\u2019s Oct. 31 launch: https://t.co/ibLwQsMJ0m https://t.co/UBIJVf6FnC"}, {"lang": "en", "author_id": "11348282", "conversation_id": "1392146756109017092", "created_at": "2021-05-11T15:57:06.000Z", "id": "1392146756109017092", "public_metrics": {"retweet_count": 737, "reply_count": 123, "like_count": 4392, "quote_count": 66}, "source": "Sprinklr", "text": "\ud83d\udd0a From 14.1 billion miles from Earth, the Voyager 1 spacecraft has detected a new cosmic \u201chum\u201d in interstellar space from the Plasma Wave System instrument aboard the craft! \n\n\ud83c\udf0a Learn about what this fascinating discovery means to us here on Earth: https://t.co/2yANyhRxQw https://t.co/V333x2A74J"}, {"lang": "en", "author_id": "11348282", "conversation_id": "1392131631666827264", "created_at": "2021-05-11T14:57:00.000Z", "id": "1392131631666827264", "referenced_tweets": [{"type": "retweeted", "id": "1392127951978774531"}], "public_metrics": {"retweet_count": 161, "reply_count": 0, "like_count": 0, "quote_count": 0}, "source": "Sprinklr", "text": "RT @NASA_Technology: \ud83d\udcfaLIVE 11 a.m. ET: NASA Senior Advisor @blal will provide the keynote @NASAArtemis update at the Lunar Surface Innovati\u2026"}, {"lang": "en", "author_id": "11348282", "conversation_id": "1391895840520904704", "created_at": "2021-05-10T23:20:03.000Z", "id": "1391895840520904704", "public_metrics": {"retweet_count": 522, "reply_count": 117, "like_count": 4230, "quote_count": 46}, "source": "Sprinklr", "text": "\ud83e\udd29 Mon., May 10: From Virginia, we're set to launch a mission to explore energy transport in space. If skies are clear, you may see it in the Eastern U.S.\n\n\ud83d\ude80 Liftoff is now no earlier than 8:04pm ET, w/a 40-min. window. \n\n\u27a1\ufe0f Follow @NASA_Wallops for news: https://t.co/Cz2jHt0iql https://t.co/f2hm3oYSD0"}, {"lang": "en", "author_id": "11348282", "conversation_id": "1391884531607740416", "created_at": "2021-05-10T22:35:06.000Z", "id": "1391884531607740416", "public_metrics": {"retweet_count": 286, "reply_count": 64, "like_count": 2485, "quote_count": 14}, "source": "Sprinklr", "text": "\ud83d\ude0e Have 3D glasses? It's time to dust them off\u2026 for science! \n\nResearchers at @NASA_Langley are using 3D modeling to better understand and measure severe weather. See weather satellite imagery like you've never seen it before \u27a1\ufe0f: https://t.co/xcO7twLzB8 https://t.co/2AXnChmxsw"}, {"lang": "en", "author_id": "11348282", "conversation_id": "1391874436916207620", "created_at": "2021-05-10T21:55:00.000Z", "id": "1391874436916207620", "referenced_tweets": [{"type": "retweeted", "id": "1391851398678069251"}], "public_metrics": {"retweet_count": 158, "reply_count": 0, "like_count": 0, "quote_count": 0}, "source": "Sprinklr", "text": "RT @ulalaunch: In 2016, @NASASolarSystem #OSIRISREx\u2019s historic journey to a near-Earth asteroid began as it lifted off on a ULA #AtlasV. Ne\u2026"}, {"lang": "en", "author_id": "11348282", "conversation_id": "1391868324640968704", "created_at": "2021-05-10T21:30:42.000Z", "id": "1391868324640968704", "public_metrics": {"retweet_count": 565, "reply_count": 70, "like_count": 3376, "quote_count": 51}, "source": "Twitter Media Studio", "text": "After nearly 5 years in space, @NASASolarSystem's #OSIRISREx mission is heading to Earth with a sample of rocks &amp; dust from a 4.5-billion-year-old asteroid! \n\n\ud83e\udea8 \u25aa\ufe0f\u25aa\ufe0f\u25aa\ufe0f\ud83d\udef0\ufe0f\u25aa\ufe0f\u25aa\ufe0f\u25aa\ufe0f \ud83c\udf0e  \n\nCheck out how its mission #ToBennuAndBack exceeded our expectations: https://t.co/91n38cmQNA https://t.co/bxtT0uXeu3"}, {"lang": "en", "author_id": "11348282", "conversation_id": "1391853501731549184", "created_at": "2021-05-10T20:31:48.000Z", "id": "1391853501731549184", "referenced_tweets": [{"type": "retweeted", "id": "1391851985532448770"}], "public_metrics": {"retweet_count": 457, "reply_count": 0, "like_count": 0, "quote_count": 0}, "source": "Twitter Web App", "text": "RT @NASASolarSystem: Mission navigation has received confirmation of burn cutoff. #OSIRISREx is headed home with a souvenir of rocks and du\u2026"}, {"lang": "en", "author_id": "11348282", "conversation_id": "1391846760012816386", "created_at": "2021-05-10T20:05:01.000Z", "id": "1391846760012816386", "public_metrics": {"retweet_count": 462, "reply_count": 36, "like_count": 2550, "quote_count": 31}, "source": "Twitter Media Studio", "text": "\ud83e\udd18 LIVE: Rock on! Join us as @NASASolarSystem's #OSIRISREx mission bids farewell to asteroid Bennu. The spacecraft will fire its thrusters &amp; start its journey home, carrying precious asteroid material that it will return to Earth in 2023: \n#ToBennuAndBack https://t.co/9sJCq6lCEz"}, {"lang": "en", "author_id": "11348282", "conversation_id": "1391838258036883456", "created_at": "2021-05-10T19:31:14.000Z", "id": "1391838258036883456", "referenced_tweets": [{"type": "retweeted", "id": "1391830439552290818"}], "public_metrics": {"retweet_count": 229, "reply_count": 0, "like_count": 0, "quote_count": 0}, "source": "Twitter Web App", "text": "RT @NASAAstrobio: \ud83d\udc4b So long and thanks for all the science!\n\nJoin us today at 4pm ET as @NASASolarSystem's #OSIRISREx mission bids farewell\u2026"}, {"lang": "en", "author_id": "11348282", "conversation_id": "1391815714688929795", "created_at": "2021-05-10T18:01:39.000Z", "id": "1391815714688929795", "public_metrics": {"retweet_count": 196, "reply_count": 49, "like_count": 2035, "quote_count": 22}, "source": "Sprinklr", "text": "Administrator @SenBillNelson announced that @Astro_CabanaBob will serve as our associate administrator, effective Mon., May 17. Mr. Cabana has served as the director of @NASAKennedy since 2008: https://t.co/izMMmB2po8 https://t.co/VSQCtjbWuI"}, {"lang": "en", "author_id": "11348282", "conversation_id": "1391803693079609348", "created_at": "2021-05-10T17:13:53.000Z", "id": "1391803693079609348", "public_metrics": {"retweet_count": 193, "reply_count": 47, "like_count": 2507, "quote_count": 15}, "source": "Sprinklr", "text": "News: Steve Jurczyk, who served as our acting administrator from Jan. 20 to May 3, 2021, and associate administrator since May 2018, will retire on Fri., May 14, after more than three decades of service to the agency: https://t.co/MxdEFtrImX https://t.co/JyR4eRrtCl"}, {"lang": "en", "author_id": "11348282", "conversation_id": "1391770190850011139", "created_at": "2021-05-10T15:00:45.000Z", "id": "1391770190850011139", "public_metrics": {"retweet_count": 380, "reply_count": 50, "like_count": 3824, "quote_count": 10}, "source": "Sprinklr", "text": "LISTEN IN: Experts from @Axiom_Space and NASA discuss details about the first private astronaut mission to the @Space_Station, slated for no earlier than January 2022: https://t.co/z1RgZwQkWS\n\nMore: https://t.co/fxlUYjTFIg https://t.co/goPLw5Y8UX"}, {"lang": "en", "author_id": "11348282", "conversation_id": "1391517217196490754", "created_at": "2021-05-09T22:15:32.000Z", "id": "1391517217196490754", "public_metrics": {"retweet_count": 682, "reply_count": 333, "like_count": 4168, "quote_count": 55}, "source": "Sprinklr", "text": "Tomorrow, our @NASASolarSystem OSIRIS-REx mission departs asteroid Bennu, carrying a sample of rocks &amp; dust for return to Earth. Set a reminder to watch live at 4pm ET as the spacecraft begins its journey home: https://t.co/L4alRfju1k\n#ToBennuAndBack https://t.co/68uLNEYv7e"}, {"lang": "en", "author_id": "11348282", "conversation_id": "1391485123816722443", "created_at": "2021-05-09T20:08:00.000Z", "id": "1391485123816722443", "public_metrics": {"retweet_count": 1303, "reply_count": 151, "like_count": 9213, "quote_count": 72}, "source": "Sprinklr", "text": "An image worth hundreds of galaxies \ud83d\udcab\n\nObserved by @NASAHubble, this image features Abell 3827, a galaxy cluster that cosmologists study to reveal more about dark matter \u2014 one of the greatest puzzles faced today. Discover more: https://t.co/OqpmLvhR2F https://t.co/RVcXsJ0Upx"}, {"lang": "en", "author_id": "11348282", "conversation_id": "1391421458673508352", "created_at": "2021-05-09T15:55:01.000Z", "id": "1391421458673508352", "public_metrics": {"retweet_count": 640, "reply_count": 97, "like_count": 5911, "quote_count": 23}, "source": "Sprinklr", "text": "\u201cSpacecraft are dependent on us in their first year as we bond. They tend to throw tantrums in their next couple of years, but we love them anyway.\u201d\n\nAt NASA, mothers and Mission Operation Managers (MOMs) happen to have a lot in common. Happy Mother's Day: https://t.co/lxZEwcop0w https://t.co/cekTlASEVj"}, {"lang": "en", "author_id": "11348282", "conversation_id": "1391404468214829058", "created_at": "2021-05-09T14:47:30.000Z", "id": "1391404468214829058", "public_metrics": {"retweet_count": 497, "reply_count": 201, "like_count": 3789, "quote_count": 85}, "source": "Sprinklr", "text": "NASA Administrator @SenBillNelson on debris from the Chinese Long March 5B rocket: \u201cSpacefaring nations must minimize the risks to people and property on Earth of re-entries of space objects and maximize transparency regarding those operations.\"\n\nMore: https://t.co/YUW0cB96he https://t.co/ZxSDm035vA"}, {"lang": "en", "author_id": "11348282", "conversation_id": "1391120267359965186", "created_at": "2021-05-08T19:58:12.000Z", "id": "1391120267359965186", "public_metrics": {"retweet_count": 348, "reply_count": 76, "like_count": 2427, "quote_count": 37}, "source": "Sprinklr", "text": "\ud83d\udce3 \ud83c\udfb6 Are you a musician inspired by exploration &amp; discovery? Break out your favorite musical instrument!\n\nWe'd love for your voice to be part of the #NASALucySoundscape, a public collection of original tunes inspired by our #LucyMission launching in 2021: https://t.co/KHQttJb6np https://t.co/012D3lFBy8"}, {"lang": "en", "author_id": "11348282", "conversation_id": "1391098381150441472", "created_at": "2021-05-08T18:31:14.000Z", "id": "1391098381150441472", "public_metrics": {"retweet_count": 546, "reply_count": 73, "like_count": 4053, "quote_count": 30}, "source": "Sprinklr", "text": "\ud83d\udc26 Tracking birds from space! The Avian Migration Aerial Surface Space project uses astronaut photos from the @Space_Station to trace bird migrations across the planet. The images map routes taken by seven endangered or threatened bird species: https://t.co/yr3t4JJ0I0 https://t.co/b7J7DozNxa"}, {"lang": "en", "author_id": "11348282", "conversation_id": "1391059570076921858", "created_at": "2021-05-08T15:57:00.000Z", "id": "1391059570076921858", "public_metrics": {"retweet_count": 602, "reply_count": 67, "like_count": 5988, "quote_count": 27}, "source": "Sprinklr", "text": "As the first Asian American to fly in space, Ellison Onizuka was a trail blazer who inspired many. In light of #AAPIHM, dive into Onizuka\u2019s amazing journey with NASA in this @GoogleArts feature: https://t.co/CPUkzJGEVm https://t.co/bJJsitwsjm"}, {"lang": "en", "author_id": "11348282", "conversation_id": "1391052339663065091", "created_at": "2021-05-08T15:28:16.000Z", "id": "1391052339663065091", "referenced_tweets": [{"type": "retweeted", "id": "1390765884214431744"}], "public_metrics": {"retweet_count": 186, "reply_count": 0, "like_count": 0, "quote_count": 0}, "source": "Twitter Web App", "text": "RT @NASA_Johnson: As we near the launch of the @NASA_SLS and the @NASA_Orion spacecraft for Artemis, the lead launch director for this firs\u2026"}, {"lang": "en", "author_id": "11348282", "conversation_id": "1390875302184857600", "created_at": "2021-05-08T03:44:47.000Z", "id": "1390875302184857600", "referenced_tweets": [{"type": "retweeted", "id": "1390335728551407623"}], "public_metrics": {"retweet_count": 119, "reply_count": 0, "like_count": 0, "quote_count": 0}, "source": "Twitter Web App", "text": "RT @hitRECordJoe: In episode 3 of #CreateTogether, I got the opportunity to sit down with a @NASA Scientist and talk about the connection b\u2026"}, {"lang": "en", "author_id": "11348282", "conversation_id": "1390832724743757824", "created_at": "2021-05-08T00:55:36.000Z", "id": "1390832724743757824", "public_metrics": {"retweet_count": 311, "reply_count": 84, "like_count": 2774, "quote_count": 14}, "source": "Sprinklr", "text": "\ud83e\ude82 Crew-1 returns home after a record-breaking mission\n\u270b @SenBillNelson is sworn in as NASA's new administrator\n\u2708\ufe0f Our experimental all-electric airplane undergoes voltage testing\n\nAll that and more in our latest episode of This Week @ NASA: https://t.co/mTxDhSb1Xu https://t.co/1nJ9X19EiR"}, {"lang": "en", "author_id": "11348282", "conversation_id": "1390829227520503809", "created_at": "2021-05-08T00:41:42.000Z", "id": "1390829227520503809", "referenced_tweets": [{"type": "retweeted", "id": "1390826543723683842"}], "public_metrics": {"retweet_count": 1787, "reply_count": 0, "like_count": 0, "quote_count": 0}, "source": "Twitter Web App", "text": "RT @NASAJPL: Excelsior! The #MarsHelicopter completed its 1st one-way trip and 5th flight on Mars. It touched down at its new location, kic\u2026"}, {"lang": "en", "author_id": "11348282", "conversation_id": "1390807412798595072", "created_at": "2021-05-07T23:15:01.000Z", "id": "1390807412798595072", "public_metrics": {"retweet_count": 278, "reply_count": 47, "like_count": 3281, "quote_count": 18}, "source": "Sprinklr", "text": "On Tues., May 11 at 10:15am ET, students from Brownsville, Texas will have an opportunity to ask @Astro_Kimbrough &amp; @Thom_Astro questions, and learn about science &amp; research on the @Space_Station. How to watch the live Earth-to-space call: https://t.co/SddfNwb8T3 https://t.co/jOvvfBLrcm"}, {"lang": "en", "author_id": "11348282", "conversation_id": "1390791050269282304", "created_at": "2021-05-07T22:10:00.000Z", "id": "1390791050269282304", "public_metrics": {"retweet_count": 271, "reply_count": 38, "like_count": 2902, "quote_count": 11}, "source": "Sprinklr", "text": "For #AAPIHM, we are celebrating @NASAPersevere mission commentator and guidance, navigation, and controls operations Lead Swati Mohan. Her work is part of the first mission to collect and cache Martian rock and regolith. Meet Swati: https://t.co/WflSTk7Hrc https://t.co/lxwKZI2Ria"}, {"lang": "en", "author_id": "11348282", "conversation_id": "1390777210500419589", "created_at": "2021-05-07T21:15:01.000Z", "id": "1390777210500419589", "public_metrics": {"retweet_count": 481, "reply_count": 74, "like_count": 4971, "quote_count": 28}, "source": "Sprinklr", "text": "We\u2019re partnering with @Axiom_Space to enable the first private astronaut mission to the @Space_Station! \n\n\ud83d\udcc5 Get the details from mission experts during a LIVE update on May 10 at 11am ET (15:00 UT).\n\nHow to tune in: https://t.co/3GPZHJXGKS https://t.co/Fr5kD0C9mg"}, {"lang": "en", "author_id": "11348282", "conversation_id": "1390747009989201921", "created_at": "2021-05-07T19:15:00.000Z", "id": "1390747009989201921", "public_metrics": {"retweet_count": 166, "reply_count": 28, "like_count": 1815, "quote_count": 4}, "source": "Sprinklr", "text": "\ud83e\ude90\u23f0 The space clock is tick...tick...ticking! Today\u2019s the final day to cast your vote for the 2021 Webby Awards, and we are up for six. \n\n\u27a1\ufe0f Get to know the projects and vote: https://t.co/wGZdVwaJoT https://t.co/cq5tDD3svI"}, {"lang": "en", "author_id": "11348282", "conversation_id": "1390728144676601857", "created_at": "2021-05-07T18:00:02.000Z", "id": "1390728144676601857", "public_metrics": {"retweet_count": 393, "reply_count": 59, "like_count": 3690, "quote_count": 20}, "source": "Sprinklr", "text": "LIVE NOW: As we prepare to send astronauts to the Moon through the @NASAArtemis program, we are testing the @NASA_Orion crew capsule that will take them there and back! Our experts are taking your questions on @Reddit until 3pm ET: https://t.co/3QG6YT3DOy https://t.co/CnBywoCgRm"}, {"lang": "en", "author_id": "11348282", "conversation_id": "1390709841874890755", "created_at": "2021-05-07T16:47:19.000Z", "id": "1390709841874890755", "public_metrics": {"retweet_count": 262, "reply_count": 47, "like_count": 2231, "quote_count": 4}, "source": "Sprinklr", "text": "This week...\n\n\ud83e\ude82  Four humans successfully returned to Earth\n\ud83d\udd2c @Space_Station astronauts investigate tissue chips\n\ud83e\uddd1\u200d\ud83d\ude80 Shane Kimbrough of @NASA_Astronauts researches space debris\n\nGet the details about these stories in this new episode of #SpaceToGround: https://t.co/kG5lqku1Ia https://t.co/2Tcd5PnWiI"}, {"lang": "en", "author_id": "11348282", "conversation_id": "1390687347453399042", "created_at": "2021-05-07T15:17:56.000Z", "id": "1390687347453399042", "public_metrics": {"retweet_count": 1471, "reply_count": 249, "like_count": 6198, "quote_count": 202}, "source": "Twitter Media Studio", "text": "\ud83d\udd0a\ud83d\udd34 New sounds from Mars: Our @NASAPersevere rover caught the beats coming from our Ingenuity #MarsHelicopter! This marks the first time a spacecraft on another planet has recorded the sounds of a separate spacecraft. \n\n\ud83c\udfa7\ud83d\ude81 Turn the volume up: https://t.co/o7zG6mQJzx https://t.co/s8Hm3dhcgg"}, {"lang": "en", "author_id": "11348282", "conversation_id": "1390456598716370947", "created_at": "2021-05-07T00:01:01.000Z", "id": "1390456598716370947", "public_metrics": {"retweet_count": 525, "reply_count": 74, "like_count": 2458, "quote_count": 63}, "source": "Sprinklr", "text": "Live in the Eastern U.S.? You may be able to see a launch from @NASAWallops! A suborbital sounding rocket is set for liftoff no earlier than Sat., May 8 at 8:02pm ET, with a mission to explore energy transport in space. \n\n\ud83e\udd29 Where &amp; when to look up: https://t.co/49gYTlhGQq https://t.co/ZtLtk5jNlt"}, {"lang": "en", "author_id": "11348282", "conversation_id": "1390437474774798339", "created_at": "2021-05-06T22:45:01.000Z", "id": "1390437474774798339", "public_metrics": {"retweet_count": 365, "reply_count": 58, "like_count": 3212, "quote_count": 18}, "source": "Sprinklr", "text": "Last October, our OSIRIS-REx spacecraft touched down &amp; captured a sample of asteroid Bennu. \n\nOn Mon., May 10 at 4pm ET, it begins the next stage of its journey #ToBennuAndBack: a two-year cruise home to Earth. Tune in live: https://t.co/rvNdnCzegl https://t.co/kEeicxwibO"}, {"lang": "en", "author_id": "11348282", "conversation_id": "1390427402002739200", "created_at": "2021-05-06T22:05:00.000Z", "id": "1390427402002739200", "referenced_tweets": [{"type": "retweeted", "id": "1390377434122489860"}], "public_metrics": {"retweet_count": 176, "reply_count": 0, "like_count": 0, "quote_count": 0}, "source": "Sprinklr", "text": "RT @NASASolarSystem: Are you a musician inspired by exploration &amp; discovery? Share your inspiration in your unique voice, and join with oth\u2026"}, {"lang": "en", "author_id": "11348282", "conversation_id": "1390422369945141257", "created_at": "2021-05-06T21:45:00.000Z", "id": "1390422369945141257", "referenced_tweets": [{"type": "retweeted", "id": "1390076339231805454"}], "public_metrics": {"retweet_count": 134, "reply_count": 0, "like_count": 0, "quote_count": 0}, "source": "Sprinklr", "text": "RT @SOFIAtelescope: May is #AAPIHeritageMonth! Project scientist Naseem Rangwala leads our scientific research &amp; was one of the first women\u2026"}, {"lang": "en", "author_id": "11348282", "conversation_id": "1390418333091172357", "created_at": "2021-05-06T21:28:57.000Z", "id": "1390418333091172357", "referenced_tweets": [{"type": "retweeted", "id": "1390401377378045955"}], "public_metrics": {"retweet_count": 1610, "reply_count": 0, "like_count": 0, "quote_count": 0}, "source": "Twitter Web App", "text": "RT @NASAJPL: Off to new places! The #MarsHelicopter is slated for its fifth flight on May 7, with data coming down at 4:31pm PT (7:31pm ET)\u2026"}, {"lang": "en", "author_id": "11348282", "conversation_id": "1390405927224942597", "created_at": "2021-05-06T20:39:40.000Z", "id": "1390405927224942597", "public_metrics": {"retweet_count": 342, "reply_count": 58, "like_count": 3014, "quote_count": 13}, "source": "Twitter Media Studio - LiveCut", "text": "\"I felt like those cartoons when they experience [g-forces] and your face is just sagging down.\u201d - @AstroVicGlover recounting his first experience reentering Earth aboard @SpaceX\u2019s Crew Dragon Resilience. https://t.co/j0W0ls0Ti6"}, {"lang": "en", "author_id": "11348282", "conversation_id": "1390402068897271813", "created_at": "2021-05-06T20:24:20.000Z", "id": "1390402068897271813", "public_metrics": {"retweet_count": 216, "reply_count": 29, "like_count": 2237, "quote_count": 8}, "source": "Twitter Media Studio - LiveCut", "text": "Is it more harrowing to splash down at night? Crew-1 astronaut Shannon Walker says everybody was so well prepared, it was no different for the crew when they splashed down on May 2. https://t.co/0l1in44fUZ"}, {"lang": "en", "author_id": "11348282", "conversation_id": "1390399603154034689", "created_at": "2021-05-06T20:14:32.000Z", "id": "1390399603154034689", "public_metrics": {"retweet_count": 480, "reply_count": 75, "like_count": 3921, "quote_count": 36}, "source": "Twitter Media Studio - LiveCut", "text": "\u201cI think we all need to be able to dream in all colors.\" \u2013 @AstroVicGlover offers his perspective on being the first Black astronaut to embark on a long-duration spaceflight aboard NASA's @SpaceX Crew-1 mission. https://t.co/nOmBwGtSJK"}, {"lang": "en", "author_id": "11348282", "conversation_id": "1390398621074563075", "created_at": "2021-05-06T20:10:38.000Z", "id": "1390398621074563075", "public_metrics": {"retweet_count": 261, "reply_count": 22, "like_count": 2124, "quote_count": 15}, "source": "Twitter Media Studio - LiveCut", "text": "\"It's purely a joy,\" says @Astro_Soichi about welcoming new crew members aboard the @Space_Station. On April 23, his @JAXA_en colleague @Aki_Hoshide launched on NASA's @SpaceX Crew-2 mission and arrived at the orbiting laboratory. https://t.co/JRQ22RVjfO"}, {"lang": "en", "author_id": "11348282", "conversation_id": "1390395059854528514", "created_at": "2021-05-06T19:56:29.000Z", "id": "1390395059854528514", "public_metrics": {"retweet_count": 558, "reply_count": 96, "like_count": 6241, "quote_count": 24}, "source": "Twitter Media Studio - LiveCut", "text": "\u201cQuite frankly, I don\u2019t know how our mission could have gone any better.\u201d - @Astro_illini praises the teams across NASA, @SpaceX, and partner agencies who helped make Crew-1 a success. https://t.co/c7pW2cPY58"}, {"lang": "en", "author_id": "11348282", "conversation_id": "1390392319292084226", "created_at": "2021-05-06T19:45:35.000Z", "id": "1390392319292084226", "public_metrics": {"retweet_count": 1383, "reply_count": 255, "like_count": 10139, "quote_count": 49}, "source": "Twitter Media Studio", "text": "LIVE: NASA\u2019s @SpaceX Crew-1 astronauts give their first update after returning to Earth. Have questions? Use #AskNASA. https://t.co/pWvaHVPi8n"}, {"lang": "en", "author_id": "11348282", "conversation_id": "1390382722699431937", "created_at": "2021-05-06T19:07:27.000Z", "id": "1390382722699431937", "referenced_tweets": [{"type": "retweeted", "id": "1390303479227428865"}], "public_metrics": {"retweet_count": 387, "reply_count": 0, "like_count": 0, "quote_count": 0}, "source": "Twitter Web App", "text": "RT @Commercial_Crew: \ud83d\udc09 @NASA's @SpaceX Crew-1 astronauts are back on planet Earth and ready to answer your questions!\n\nJoin us today at 3:4\u2026"}, {"lang": "en", "author_id": "11348282", "conversation_id": "1390366038886436868", "created_at": "2021-05-06T18:01:10.000Z", "id": "1390366038886436868", "public_metrics": {"retweet_count": 239, "reply_count": 29, "like_count": 2229, "quote_count": 17}, "source": "Twitter for iPhone", "text": "HAPPENING NOW: @NASAEarth and university scientists answer your questions on @Reddit! \r\r\ud83c\udf33\ud83d\udc49 Don\u2019t miss this opportunity to talk directly to experts involved with tree science and how they can regulate climate change. \r\rSubmit your ?s here: https://t.co/YBEZVz4bTb https://t.co/KweLVIRE5V"}, {"lang": "en", "author_id": "11348282", "conversation_id": "1390363234377601028", "created_at": "2021-05-06T17:50:01.000Z", "id": "1390363234377601028", "referenced_tweets": [{"type": "retweeted", "id": "1390361809941671937"}], "public_metrics": {"retweet_count": 323, "reply_count": 0, "like_count": 0, "quote_count": 0}, "source": "Twitter Web App", "text": "RT @Commercial_Crew: Launch Alert \ud83d\ude80 @NASA and @BoeingSpace are targeting Friday, July 30 at 2:53 p.m. ET for the launch of the Orbital Flig\u2026"}, {"lang": "en", "author_id": "11348282", "conversation_id": "1390352081798586373", "created_at": "2021-05-06T17:05:42.000Z", "id": "1390352081798586373", "referenced_tweets": [{"type": "retweeted", "id": "1390294023437422598"}], "public_metrics": {"retweet_count": 174, "reply_count": 0, "like_count": 0, "quote_count": 0}, "source": "Twitter Web App", "text": "RT @NASAInterns: We are proud to celebrate Asian American &amp; Pacific Islander Heritage Month w/ @NASAPeople who contribute to @NASA missions\u2026"}, {"lang": "en", "author_id": "11348282", "conversation_id": "1390348387770413061", "created_at": "2021-05-06T16:51:01.000Z", "id": "1390348387770413061", "public_metrics": {"retweet_count": 214, "reply_count": 35, "like_count": 2015, "quote_count": 11}, "source": "Sprinklr", "text": "See the iconic golden mirror of @NASAWebb for the last time on Earth during a virtual briefing Tues., May 11 at 1pm ET. Hear NASA &amp; @NorthropGrumman officials discuss the mission\u2019s next steps.\n\n\ud83d\udc49 Questions? Use #NASAWebb.\nGet more details: https://t.co/hnZ3kCp5CU https://t.co/ba2ie7nnMa"}, {"lang": "en", "author_id": "11348282", "conversation_id": "1390097732686290948", "created_at": "2021-05-06T00:15:00.000Z", "id": "1390097732686290948", "public_metrics": {"retweet_count": 298, "reply_count": 70, "like_count": 3058, "quote_count": 10}, "source": "Sprinklr", "text": "\ud83e\ude90\ud83e\udd88 From alien planets to whale sharks, six of our projects have been nominated for the 2021 Webby Awards! \n\n\ud83d\uddf3\ufe0f Have a look at the nominees and cast your vote by Friday, May 7!: https://t.co/GczY3mSLKo https://t.co/9rABoXg6gW"}, {"lang": "en", "author_id": "11348282", "conversation_id": "1390082130705883140", "created_at": "2021-05-05T23:13:01.000Z", "id": "1390082130705883140", "public_metrics": {"retweet_count": 177, "reply_count": 49, "like_count": 1707, "quote_count": 5}, "source": "Sprinklr", "text": "\ud83d\udce1 @NASASCaN provides communications &amp; navigation in space, including for @Commercial_Crew. On the new episode of our \"Invisible Network\" podcast, engineers describe their role in ensuring the success of the first Crew Dragon flights with astronauts: https://t.co/oxJIUIdvNK https://t.co/RDz0UAqPR5"}, {"lang": "en", "author_id": "11348282", "conversation_id": "1390051685800849408", "created_at": "2021-05-05T21:12:02.000Z", "id": "1390051685800849408", "public_metrics": {"retweet_count": 332, "reply_count": 63, "like_count": 4300, "quote_count": 24}, "source": "Sprinklr", "text": "On Thurs., May 6 at 10:30am ET, students from New York will join a live Earth-to-space call with @Astro_Megan &amp; @Thom_Astro on the @Space_Station. How to watch: https://t.co/0Nrs71GoEa https://t.co/RKSVzDAYmi"}, {"lang": "en", "author_id": "11348282", "conversation_id": "1390032805820870656", "created_at": "2021-05-05T19:57:01.000Z", "id": "1390032805820870656", "public_metrics": {"retweet_count": 934, "reply_count": 147, "like_count": 7501, "quote_count": 65}, "source": "Sprinklr", "text": "60 years ago today, astronaut Alan Shepard became the first American to travel in space, climbing ~116 miles (188 km) above Earth! Shortly after, President John F. Kennedy committed the United States to a lunar landing before the end of the decade: https://t.co/1syroEq84g https://t.co/TO1GtAUgZA"}, {"lang": "en", "author_id": "11348282", "conversation_id": "1390017450431877120", "created_at": "2021-05-05T18:56:00.000Z", "id": "1390017450431877120", "referenced_tweets": [{"type": "retweeted", "id": "1390008020437020674"}], "public_metrics": {"retweet_count": 84, "reply_count": 0, "like_count": 0, "quote_count": 0}, "source": "Sprinklr", "text": "RT @NASA_APPEL: Dive into our new \ud83c\udf99\ufe0f ep., 'Spacecraft Window Design,' with Lynda Estes\u2014@NASA_Orion's and @Commercial_Crew's expert on space\u2026"}, {"lang": "en", "author_id": "11348282", "conversation_id": "1390005307426869248", "created_at": "2021-05-05T18:07:44.000Z", "id": "1390005307426869248", "referenced_tweets": [{"type": "quoted", "id": "1389988261175742467"}], "public_metrics": {"retweet_count": 122, "reply_count": 35, "like_count": 1351, "quote_count": 2}, "source": "Twitter Web App", "text": "LIVE: Teacher-turned-astronaut @Astro_Ricky describes his career journey and answers questions: https://t.co/ak8jNgTImV"}, {"lang": "en", "author_id": "11348282", "conversation_id": "1389994549972455426", "created_at": "2021-05-05T17:25:00.000Z", "id": "1389994549972455426", "referenced_tweets": [{"type": "retweeted", "id": "1389969938744492041"}], "public_metrics": {"retweet_count": 170, "reply_count": 0, "like_count": 0, "quote_count": 0}, "source": "Sprinklr", "text": "RT @NASA_Technology: The government is getting America's small businesses back on track! We invest millions of dollars in them each year an\u2026"}, {"lang": "en", "author_id": "11348282", "conversation_id": "1389975029459398669", "created_at": "2021-05-05T16:07:26.000Z", "id": "1389975029459398669", "public_metrics": {"retweet_count": 435, "reply_count": 80, "like_count": 2748, "quote_count": 20}, "source": "Sprinklr", "text": "NOW: To mark the 60th anniversary of Americans in space, @NASAHistory and @AirAndSpace experts are answering your questions on @Reddit about the history of human spaceflight: https://t.co/FvLoCqPfQb https://t.co/aUDMevX3MX"}, {"in_reply_to_user_id": "3068863500", "lang": "en", "author_id": "11348282", "conversation_id": "1389744478261583877", "created_at": "2021-05-05T15:30:25.000Z", "id": "1389965716074471431", "referenced_tweets": [{"type": "replied_to", "id": "1389744478261583877"}], "public_metrics": {"retweet_count": 3, "reply_count": 1, "like_count": 1, "quote_count": 1}, "source": "Twitter Web App", "text": "@visimpressa Good question! There are no orbiters around Titan to help transmit. Therefore, Dragonfly will use direct-to-Earth communications &amp; beam all uplink and downlink communications from its antenna directly to NASA\u2019s Deep Space Network. Find out more: https://t.co/xImh4AspkF"}, {"lang": "en", "author_id": "11348282", "conversation_id": "1389965277299937283", "created_at": "2021-05-05T15:28:41.000Z", "id": "1389965277299937283", "referenced_tweets": [{"type": "retweeted", "id": "1389958067102568450"}], "public_metrics": {"retweet_count": 553, "reply_count": 0, "like_count": 0, "quote_count": 0}, "source": "Twitter Web App", "text": "RT @NASAhistory: Some heroes don't wear spacesuits!\n\nAlan Shepard's flight wouldn't have been possible without mathematician Katherine John\u2026"}, {"lang": "en", "author_id": "11348282", "conversation_id": "1389958300284948480", "created_at": "2021-05-05T15:00:57.000Z", "id": "1389958300284948480", "public_metrics": {"retweet_count": 344, "reply_count": 49, "like_count": 3531, "quote_count": 7}, "source": "Sprinklr", "text": "LIVE: A look at 60 years of Americans in space, with our head of human spaceflight @KathyLueders, experts from @NASAHistory and @AirAndSpace, with remarks from @Astro_Jeanette: https://t.co/z1RgZwQkWS\n\nAt 12pm ET (16:00 UT), join us on @Reddit's r/history to learn more. https://t.co/8y7LtxLIG8"}, {"lang": "en", "author_id": "11348282", "conversation_id": "1389951533912109059", "created_at": "2021-05-05T14:34:04.000Z", "id": "1389951533912109059", "public_metrics": {"retweet_count": 770, "reply_count": 56, "like_count": 3811, "quote_count": 54}, "source": "Sprinklr", "text": "\u201cWhat a beautiful view.\u201d\n\nAlan Shepard became the first American in space 60 years ago (May 5, 1961) when Freedom 7 lifted off atop a Mercury-Redstone rocket. The 15-minute flight gave us valuable data on how humans respond to microgravity: https://t.co/j7XdaOccRt https://t.co/yHZKsspHGd"}, {"in_reply_to_user_id": "11348282", "lang": "en", "author_id": "11348282", "conversation_id": "1389742899638771717", "created_at": "2021-05-05T00:45:03.000Z", "id": "1389742905573707778", "referenced_tweets": [{"type": "replied_to", "id": "1389742899638771717"}], "public_metrics": {"retweet_count": 277, "reply_count": 42, "like_count": 2715, "quote_count": 16}, "source": "Sprinklr", "text": "\ud83d\udcfa Starting at 8:30am, watch archival footage and a replay of the May 5, 1961 launch broadcast. \n\n\ud83d\ude80 At 11am, join @NASAHistory and @AirAndSpace for a discussion on six decades of American spaceflight. \n\n\ud83d\udcbb And at 12pm, they'll answer your ?s on @Reddit: \n\nhttps://t.co/z1RgZwQkWS https://t.co/kWxA0VVlgn"}, {"lang": "en", "author_id": "11348282", "conversation_id": "1389742899638771717", "created_at": "2021-05-05T00:45:02.000Z", "id": "1389742899638771717", "public_metrics": {"retweet_count": 981, "reply_count": 114, "like_count": 8359, "quote_count": 43}, "source": "Sprinklr", "text": "Tomorrow marks the 60th anniversary of Alan Shepard's historic flight aboard Freedom 7, making him the first American in space. Here a short thread on how you can celebrate with us (all times Eastern) \u2b07\ufe0f https://t.co/dcnlopXJAl"}, {"lang": "en", "author_id": "11348282", "conversation_id": "1389725811268280322", "created_at": "2021-05-04T23:37:07.000Z", "id": "1389725811268280322", "public_metrics": {"retweet_count": 523, "reply_count": 72, "like_count": 3352, "quote_count": 36}, "source": "Sprinklr", "text": "We've discovered thousands of exoplanets (planets beyond our solar system).\n\n\ud83c\udf0b Lava planets \u2705\n\ud83e\udd5a Egg-shaped worlds \u2705\n\u2600\ufe0f\u2600\ufe0f Planets with multiple suns \u2705\n\u26ab \ufe0fPlanets with no sun at all! \u2705\n\nWhat can we learn from all this weird, wondrous variety? https://t.co/spiXTKssBh https://t.co/mmw1MEGdTU"}, {"lang": "en", "author_id": "11348282", "conversation_id": "1389691442294136833", "created_at": "2021-05-04T21:20:33.000Z", "id": "1389691442294136833", "public_metrics": {"retweet_count": 515, "reply_count": 80, "like_count": 3715, "quote_count": 50}, "source": "Sprinklr", "text": "Teachers open up our universe! \ud83d\udcab\nWhether in-person or on a screen, educators everywhere have adapted and continued to inspire and challenge the next generation of explorers to reach for the stars: https://t.co/c3He8noGVQ\n\nFrom the @Space_Station, happy #TeacherAppreciationWeek! https://t.co/h1mlDlbYR5"}, {"lang": "en", "author_id": "11348282", "conversation_id": "1389656225806233600", "created_at": "2021-05-04T19:00:37.000Z", "id": "1389656225806233600", "public_metrics": {"retweet_count": 496, "reply_count": 62, "like_count": 3192, "quote_count": 18}, "source": "Twitter Media Studio", "text": "\ud83d\ude81\ud83d\udd34 WATCH: On the latest edition of #NASAScience Live, we discuss the exciting future of extraterrestrial flight with experts from the Ingenuity #MarsHelicopter team and upcoming Dragonfly mission team. \n\nHave Qs? Use #AskNASA: https://t.co/7jn1Zc4cvD"}, {"lang": "en", "author_id": "11348282", "conversation_id": "1389652295399444488", "created_at": "2021-05-04T18:45:00.000Z", "id": "1389652295399444488", "referenced_tweets": [{"type": "retweeted", "id": "1389622466931216391"}], "public_metrics": {"retweet_count": 123, "reply_count": 0, "like_count": 0, "quote_count": 0}, "source": "Sprinklr", "text": "RT @NASAAstrobio: What\u2019s next for the future of extraterrestrial flight? Join experts to learn about #MarsHelicopter and @NASA\u2019s upcoming #\u2026"}, {"lang": "en", "author_id": "11348282", "conversation_id": "1389646312354861056", "created_at": "2021-05-04T18:21:13.000Z", "id": "1389646312354861056", "referenced_tweets": [{"type": "retweeted", "id": "1389641934231199754"}], "public_metrics": {"retweet_count": 486, "reply_count": 0, "like_count": 0, "quote_count": 0}, "source": "Twitter Web App", "text": "RT @NASASolarSystem: On #StarWarsDay, let us remind you the odds of successfully navigating an asteroid field are\u2026quite good. \n- #OSIRISREx\u2026"}, {"lang": "en", "author_id": "11348282", "conversation_id": "1389639711396933632", "created_at": "2021-05-04T17:55:00.000Z", "id": "1389639711396933632", "referenced_tweets": [{"type": "retweeted", "id": "1389235806041083907"}], "public_metrics": {"retweet_count": 85, "reply_count": 0, "like_count": 0, "quote_count": 0}, "source": "Sprinklr", "text": "RT @NASASTEM: What's better than one #NASASTEM Stars episode?\ud83e\udd14 TWO new NASA STEM Stars episodes!\ud83e\udd29\n \n\ud83d\udd2d @NASAWebb Astrophysicist Dr. Kartik S\u2026"}, {"lang": "en", "author_id": "11348282", "conversation_id": "1389627885875613698", "created_at": "2021-05-04T17:08:00.000Z", "id": "1389627885875613698", "public_metrics": {"retweet_count": 1511, "reply_count": 77, "like_count": 8240, "quote_count": 76}, "source": "Sprinklr", "text": "In a galaxy far, far away\u2026\nSkywalker\u2019s home planet Tatooine in \u201cStar Wars,\u201d which orbited 2 stars, wasn't just cinematic invention. Thanks to our @NASAUniverse missions, we\u2019re able to learn more about binary stars. Take a look &amp; #MaytheFourthBeWithYou: https://t.co/YR3tVuxE0O https://t.co/Zww4CBFFxX"}, {"lang": "en", "author_id": "11348282", "conversation_id": "1389620582447296520", "created_at": "2021-05-04T16:38:59.000Z", "id": "1389620582447296520", "referenced_tweets": [{"type": "retweeted", "id": "1389581790868905991"}], "public_metrics": {"retweet_count": 2523, "reply_count": 0, "like_count": 0, "quote_count": 0}, "source": "Twitter Web App", "text": "RT @NASAHubble: #MayThe4thBeWithYou! Hubble captured this view of a celestial \u201clightsaber\u201d that\u2019s called HH 24. But it\u2019s not in a galaxy fa\u2026"}, {"lang": "en", "author_id": "11348282", "conversation_id": "1389612255814295557", "created_at": "2021-05-04T16:05:54.000Z", "id": "1389612255814295557", "referenced_tweets": [{"type": "retweeted", "id": "1389607067485458440"}], "public_metrics": {"retweet_count": 181, "reply_count": 0, "like_count": 0, "quote_count": 0}, "source": "Twitter Web App", "text": "RT @NASAGoddard: Tired of looking in Alderaan places for your inspiration?\n\nCheck out our SVS. These *are* the visuals you\u2019re looking for.\u2026"}, {"lang": "en", "author_id": "11348282", "conversation_id": "1389609011499225090", "created_at": "2021-05-04T15:53:00.000Z", "id": "1389609011499225090", "public_metrics": {"retweet_count": 3768, "reply_count": 222, "like_count": 17561, "quote_count": 279}, "source": "Sprinklr", "text": "In 1977, Star Wars introduced the two-sun, \u201ccircumbinary\u201d planet Tatooine \u2014 but astronomers didn\u2019t know such solar systems existed.\n\n\ud83e\udd2f Decades later, they began finding them! Our TESS mission discovered this two-sun planet in 2020: https://t.co/XV7JmdbFTy\n\n#MayTheFourthBeWithYou https://t.co/vBbAqzVpcK"}, {"lang": "en", "author_id": "11348282", "conversation_id": "1389383037176197123", "created_at": "2021-05-04T00:55:04.000Z", "id": "1389383037176197123", "public_metrics": {"retweet_count": 943, "reply_count": 126, "like_count": 8960, "quote_count": 27}, "source": "Sprinklr", "text": "\ud83d\udcf8 NEW PHOTO DROP: We've released new images from the @SpaceX Crew Dragon Endeavour's May 2 splashdown with Crew-1 astronauts @AstroVicGlover, @Astro_illini, Shannon Walker, &amp; @Astro_Soichi!\n\n\ud83e\udd29 Check \u2018em out via @NASAHQPhoto: https://t.co/431JM1SYtj https://t.co/4FspWV6npy"}, {"lang": "en", "author_id": "11348282", "conversation_id": "1389357916013072385", "created_at": "2021-05-03T23:15:14.000Z", "id": "1389357916013072385", "public_metrics": {"retweet_count": 388, "reply_count": 100, "like_count": 3023, "quote_count": 40}, "source": "Sprinklr", "text": "Today, @SenBillNelson was sworn in as our new administrator by @VP Kamala Harris. As our 14th administrator, Nelson will lead our mission of exploration and innovation. More: https://t.co/mSRkgsCRrA https://t.co/8PqWO3MsIC"}, {"lang": "en", "author_id": "11348282", "conversation_id": "1389341502371946497", "created_at": "2021-05-03T22:10:01.000Z", "id": "1389341502371946497", "public_metrics": {"retweet_count": 510, "reply_count": 206, "like_count": 5288, "quote_count": 34}, "source": "Sprinklr", "text": "After 168 days in space, NASA\u2019s @SpaceX Crew-1 astronauts arrived home on May 2. \n\n\ud83d\udcc5 On May 6 at 3:45pm ET (19:45 UT), hear from the crew LIVE during their first Q&amp;A back on Earth. \n\nSubmit your ?s about their historic mission using #AskNASA. Details: https://t.co/NqtnyW475M https://t.co/BbsEYpAPwA"}, {"lang": "en", "author_id": "11348282", "conversation_id": "1389327847102238724", "created_at": "2021-05-03T21:15:45.000Z", "id": "1389327847102238724", "referenced_tweets": [{"type": "retweeted", "id": "1389324135378128898"}], "public_metrics": {"retweet_count": 141, "reply_count": 0, "like_count": 0, "quote_count": 0}, "source": "Twitter Web App", "text": "RT @NASAhistory: In celebration of Alan Shepard's historic flight and the past 60 years of Americans in space, @NASAhistory &amp; @airandspace\u2026"}, {"lang": "en", "author_id": "11348282", "conversation_id": "1389311299914551306", "created_at": "2021-05-03T20:10:00.000Z", "id": "1389311299914551306", "public_metrics": {"retweet_count": 391, "reply_count": 50, "like_count": 4508, "quote_count": 6}, "source": "Sprinklr", "text": "\u27a1\ufe0f Media accreditation is open for the launch of the next @SpaceX delivery of @ISS_Research, supplies, &amp; more to the @Space_Station, targeted for June 3! This will be the second cargo resupply mission on the upgraded version of the Dragon spacecraft: https://t.co/6MCwymcUGy https://t.co/URNCNfJoDC"}, {"lang": "en", "author_id": "11348282", "conversation_id": "1389301770992635915", "created_at": "2021-05-03T19:32:08.000Z", "id": "1389301770992635915", "referenced_tweets": [{"type": "retweeted", "id": "1389299862638895108"}], "public_metrics": {"retweet_count": 1224, "reply_count": 0, "like_count": 0, "quote_count": 0}, "source": "Twitter Web App", "text": "RT @VP: .@NASA is critical to U.S. national and economic security. With decades of experience and as a former astronaut, Bill Nelson will a\u2026"}, {"lang": "en", "author_id": "11348282", "conversation_id": "1389280085170135041", "created_at": "2021-05-03T18:05:58.000Z", "id": "1389280085170135041", "public_metrics": {"retweet_count": 562, "reply_count": 86, "like_count": 5263, "quote_count": 16}, "source": "Sprinklr", "text": "LIVE NOW: @NASAUniverse experts answer your questions on @Reddit!\n \n\ud83d\udd2d Ask them anything about how they use an X-ray telescope on the @Space_Station to study the remnants of massive exploded stars, environments around black holes, &amp; other cosmic phenomena: https://t.co/35UHwbxPny https://t.co/IyIzasPckM"}, {"lang": "en", "author_id": "11348282", "conversation_id": "1389259902208593925", "created_at": "2021-05-03T16:45:46.000Z", "id": "1389259902208593925", "referenced_tweets": [{"type": "retweeted", "id": "1389259553750097928"}], "public_metrics": {"retweet_count": 300, "reply_count": 0, "like_count": 0, "quote_count": 0}, "source": "Twitter Web App", "text": "RT @nasahqphoto: Former Senator Bill Nelson was ceremonially sworn in as the 14th @NASA Administrator today by @VP Kamala Harris. Check out\u2026"}, {"lang": "en", "author_id": "11348282", "conversation_id": "1389200516455010307", "created_at": "2021-05-03T12:49:47.000Z", "id": "1389200516455010307", "referenced_tweets": [{"type": "retweeted", "id": "1388865932286562310"}], "public_metrics": {"retweet_count": 1382, "reply_count": 0, "like_count": 0, "quote_count": 0}, "source": "Twitter Web App", "text": "RT @AstroVicGlover: Home! Mission Complete. https://t.co/dVqCjF1UUd"}, {"lang": "en", "author_id": "11348282", "conversation_id": "1388962755143688203", "created_at": "2021-05-02T21:05:01.000Z", "id": "1388962755143688203", "public_metrics": {"retweet_count": 529, "reply_count": 86, "like_count": 4577, "quote_count": 26}, "source": "Sprinklr", "text": "\"With my disability, people tend to make assumptions about what I can and can\u2019t do.\" In a new episode of our #GravityAssist podcast, hear Dana Bolles discuss how she has dealt with other people's assumptions, and her passion for inspiring students in STEM: https://t.co/01Guw9X12c https://t.co/RTCC29TvWh"}, {"lang": "en", "author_id": "11348282", "conversation_id": "1388918713475338242", "created_at": "2021-05-02T18:10:00.000Z", "id": "1388918713475338242", "public_metrics": {"retweet_count": 1233, "reply_count": 140, "like_count": 8029, "quote_count": 76}, "source": "Sprinklr", "text": "A necklace of cosmic proportions \ud83d\udc8e\n\n@NASAHubble has uncovered an improved, fresh view of the intriguing Necklace Nebula with new techniques. Find out how a pair of tightly orbiting Sun-like stars produce this spectacular nebula:\nhttps://t.co/zn10YcLtrY https://t.co/26E6GQGuIY"}, {"lang": "en", "author_id": "11348282", "conversation_id": "1388791635568381953", "created_at": "2021-05-02T09:45:03.000Z", "id": "1388791635568381953", "public_metrics": {"retweet_count": 4603, "reply_count": 598, "like_count": 34611, "quote_count": 428}, "source": "Sprinklr", "text": "Let\u2019s give NASA's @SpaceX Crew-1 astronauts a hand!\n\n\ud83d\udc4f Welcome home. \n\nIn the most fitting fashion, their mission, which certified the return of astronaut launches from the U.S., ended with an equally historic nighttime splashdown at 2:56am ET (06:56 UT): https://t.co/xQUMykAB30 https://t.co/pt3lSHkmlH"}, {"lang": "en", "author_id": "11348282", "conversation_id": "1388790270351843328", "created_at": "2021-05-02T09:39:37.000Z", "id": "1388790270351843328", "public_metrics": {"retweet_count": 206, "reply_count": 24, "like_count": 1801, "quote_count": 8}, "source": "Twitter Media Studio - LiveCut", "text": "What are the differences between the SpaceX Crew-1 &amp; Crew-2 Dragon capsules? There are a few modifications: to the propulsion systems, software, a battery upgrade with improved lifetime, and a fly-around capability. @Commercial_Crew manager Steve Stich responds to a question: https://t.co/7XfiHGFi6y"}, {"in_reply_to_user_id": "42086886", "lang": "en", "author_id": "11348282", "conversation_id": "1388786800647229443", "created_at": "2021-05-02T09:36:19.000Z", "id": "1388789439061708802", "referenced_tweets": [{"type": "replied_to", "id": "1388786800647229443"}], "public_metrics": {"retweet_count": 2, "reply_count": 1, "like_count": 12, "quote_count": 1}, "source": "TweetDeck", "text": "@SmileSimplify No, SpaceX is in the process of building a new Crew Dragon spacecraft for Crew-3."}, {"in_reply_to_user_id": "3748491678", "lang": "en", "author_id": "11348282", "conversation_id": "1388782382501740551", "created_at": "2021-05-02T09:35:04.000Z", "id": "1388789126334488578", "referenced_tweets": [{"type": "replied_to", "id": "1388782382501740551"}], "public_metrics": {"retweet_count": 5, "reply_count": 1, "like_count": 7, "quote_count": 1}, "source": "TweetDeck", "text": "@IamMissSindy The Dragon capsules are reusable! Our recently launched Crew-2 mission was the first time we\u2019ve flown a reused Crew Dragon spacecraft. They can be reused up to four times totaling five flights for up to 210 days on orbit."}, {"lang": "en", "author_id": "11348282", "conversation_id": "1388788506449879045", "created_at": "2021-05-02T09:32:37.000Z", "id": "1388788506449879045", "public_metrics": {"retweet_count": 234, "reply_count": 30, "like_count": 2555, "quote_count": 9}, "source": "Twitter Media Studio - LiveCut", "text": "\"Everything came together and resulted in these record-breaking times for getting the Dragon out of the water and the crew out of Dragon.\" \u2014 @SpaceX's Hans Koenigsmann on recovery operations following tonight's splashdown of the Crew-1 mission. https://t.co/NmNg2t0OpZ"}, {"lang": "en", "author_id": "11348282", "conversation_id": "1388785093901234176", "created_at": "2021-05-02T09:19:03.000Z", "id": "1388785093901234176", "public_metrics": {"retweet_count": 222, "reply_count": 28, "like_count": 2182, "quote_count": 11}, "source": "Twitter Media Studio - LiveCut", "text": "\"All four crew members are doing really well. We got the capsule on board \u2014 Resilience on board \u2014 SpaceX's recovery ship without any trouble.\" \u2014 Holly Ridings, chief flight director, @NASA_Johnson, on tonight's Crew-1 mission splashdown. https://t.co/koCCG8o1o8"}, {"in_reply_to_user_id": "19694902", "lang": "en", "author_id": "11348282", "conversation_id": "1388745747424813061", "created_at": "2021-05-02T09:13:37.000Z", "id": "1388783724834263040", "referenced_tweets": [{"type": "replied_to", "id": "1388745747424813061"}], "public_metrics": {"retweet_count": 5, "reply_count": 0, "like_count": 6, "quote_count": 1}, "source": "Twitter Web App", "text": "@psbfoto The last and only other nighttime splashdown of a U.S. crewed spacecraft was in 1968 with the return of our Apollo 8 astronauts."}, {"in_reply_to_user_id": "1317509162968870912", "lang": "en", "author_id": "11348282", "conversation_id": "1388781346198147074", "created_at": "2021-05-02T09:12:53.000Z", "id": "1388783544047226883", "referenced_tweets": [{"type": "replied_to", "id": "1388781346198147074"}], "public_metrics": {"retweet_count": 4, "reply_count": 0, "like_count": 5, "quote_count": 1}, "source": "Twitter Web App", "text": "@DeeganDaGoat The Crew-1 mission astronauts spent approximately 167 days on the @Space_Station, completing 2,688 orbits of Earth!"}, {"lang": "en", "author_id": "11348282", "conversation_id": "1388780439993823232", "created_at": "2021-05-02T09:00:33.000Z", "id": "1388780439993823232", "public_metrics": {"retweet_count": 426, "reply_count": 36, "like_count": 2555, "quote_count": 12}, "source": "Twitter Media Studio", "text": "LIVE NOW: After this morning\u2019s successful return of NASA\u2019s SpaceX Crew-1 to Earth, mission experts share post-splashdown updates. Stay tuned to hear from: \n\n@NASAKennedy\n@NASA_Johnson\n@SpaceX\n@JAXA_en https://t.co/1Bzu9gg8xh"}, {"lang": "en", "author_id": "11348282", "conversation_id": "1388775431235584000", "created_at": "2021-05-02T08:40:39.000Z", "id": "1388775431235584000", "referenced_tweets": [{"type": "retweeted", "id": "1388770832181305353"}], "public_metrics": {"retweet_count": 1760, "reply_count": 0, "like_count": 0, "quote_count": 0}, "source": "Twitter Web App", "text": "RT @nasahqphoto: Splashdown! The @SpaceX Crew Dragon, Resilience, lands in the Gulf of Mexico after undocking from @Space_Station with Crew\u2026"}, {"lang": "en", "author_id": "11348282", "conversation_id": "1388766204832194560", "created_at": "2021-05-02T08:03:59.000Z", "id": "1388766204832194560", "referenced_tweets": [{"type": "retweeted", "id": "1388764489466662912"}], "public_metrics": {"retweet_count": 518, "reply_count": 0, "like_count": 0, "quote_count": 0}, "source": "Twitter Web App", "text": "RT @NASAKennedy: \u2705 Mission complete! @Astro_illini, @AstroVicGlover, Shannon Walker and @Astro_Soichi splashed down off the Florida coast a\u2026"}], "meta": {"oldest_id": "1388766204832194560", "newest_id": "1392573297762635779", "result_count": 100, "next_token": "7140dibdnow9c7btw3w4dhd3owd0mhhu221stvkvrr7lc"}}