{"data": [{"source": "Twitter for iPhone", "public_metrics": {"retweet_count": 8838, "reply_count": 1808, "like_count": 71630, "quote_count": 1264}, "text": "Cybertruck in NYC https://t.co/Q7JnSo1QoX", "author_id": "13298072", "conversation_id": "1391073650971926532", "lang": "en", "created_at": "2021-05-08T16:52:57.000Z", "id": "1391073650971926532"}, {"source": "Twitter for iPhone", "public_metrics": {"retweet_count": 3620, "reply_count": 0, "like_count": 0, "quote_count": 0}, "referenced_tweets": [{"type": "retweeted", "id": "1390843806086488069"}], "text": "RT @ericrihlmann: Tesla Cybertruck in Times Square.\n\n#cybertruck https://t.co/65BIn9WNsY", "author_id": "13298072", "conversation_id": "1391069842443313158", "lang": "en", "created_at": "2021-05-08T16:37:49.000Z", "id": "1391069842443313158"}, {"source": "Twitter for iPhone", "public_metrics": {"retweet_count": 16455, "reply_count": 0, "like_count": 0, "quote_count": 0}, "referenced_tweets": [{"type": "retweeted", "id": "1390839584225955847"}], "text": "RT @elonmusk: Cybertruck prototype in New York this weekend", "author_id": "13298072", "conversation_id": "1390960784587563008", "lang": "en", "created_at": "2021-05-08T09:24:28.000Z", "id": "1390960784587563008"}, {"source": "Twitter for iPhone", "public_metrics": {"retweet_count": 835, "reply_count": 0, "like_count": 0, "quote_count": 0}, "referenced_tweets": [{"type": "retweeted", "id": "1390765882461147139"}], "text": "RT @TeslaCharging: 25k Superchargers around the world  \u2014 and counting https://t.co/UzyFergQJ3", "author_id": "13298072", "conversation_id": "1390766949517467653", "lang": "en", "created_at": "2021-05-07T20:34:14.000Z", "id": "1390766949517467653"}, {"source": "Twitter for iPhone", "public_metrics": {"retweet_count": 1147, "reply_count": 888, "like_count": 14183, "quote_count": 132}, "referenced_tweets": [{"type": "quoted", "id": "1380722130438868994"}], "text": "Your Tesla will continue to improve long after you bought it https://t.co/wepMWlVFeN", "author_id": "13298072", "conversation_id": "1387413976296919041", "lang": "en", "created_at": "2021-04-28T14:30:43.000Z", "id": "1387413976296919041"}, {"source": "Twitter for iPhone", "public_metrics": {"retweet_count": 11511, "reply_count": 0, "like_count": 0, "quote_count": 0}, "referenced_tweets": [{"type": "retweeted", "id": "1385108424761872387"}], "text": "RT @elonmusk: Tesla Solar + Powerwall battery enables consumers to be their own utility", "author_id": "13298072", "conversation_id": "1385178256509480967", "lang": "en", "created_at": "2021-04-22T10:26:46.000Z", "id": "1385178256509480967"}, {"source": "Twitter for iPhone", "public_metrics": {"retweet_count": 19202, "reply_count": 0, "like_count": 0, "quote_count": 0}, "referenced_tweets": [{"type": "retweeted", "id": "1383548841438236674"}], "text": "RT @elonmusk: Tesla with Autopilot engaged now approaching 10 times lower chance of accident than average vehicle", "author_id": "13298072", "conversation_id": "1383553917234016263", "lang": "en", "created_at": "2021-04-17T22:52:13.000Z", "id": "1383553917234016263"}, {"source": "Twitter for iPhone", "public_metrics": {"retweet_count": 14811, "reply_count": 6180, "like_count": 191359, "quote_count": 2233}, "text": "Cybertruck at Giga Texas https://t.co/c1RuektPnN", "author_id": "13298072", "conversation_id": "1382935987681116160", "lang": "tl", "created_at": "2021-04-16T05:56:47.000Z", "id": "1382935987681116160"}, {"source": "Twitter for iPhone", "public_metrics": {"retweet_count": 3642, "reply_count": 2819, "like_count": 90587, "quote_count": 617}, "text": "Tesla seats factory https://t.co/X4PLPjuuj4", "author_id": "13298072", "conversation_id": "1379210038141665281", "lang": "en", "created_at": "2021-04-05T23:11:12.000Z", "id": "1379210038141665281"}, {"source": "Twitter for iPhone", "public_metrics": {"retweet_count": 2082, "reply_count": 1286, "like_count": 30363, "quote_count": 243}, "text": "Model 3 deliveries in Europe https://t.co/fiBNp2a6pG", "author_id": "13298072", "conversation_id": "1377618168705859585", "lang": "da", "created_at": "2021-04-01T13:45:40.000Z", "id": "1377618168705859585"}, {"source": "Twitter for iPhone", "public_metrics": {"retweet_count": 4728, "reply_count": 3102, "like_count": 56518, "quote_count": 399}, "text": "6,000+ Superchargers across Europe \u2014 at 600 locations and counting!\n\n\ud83d\udcf8 by @EPavlic, @MinimalDuck &amp; @_better_e https://t.co/Yf36HRO9MC", "author_id": "13298072", "conversation_id": "1375118425362628613", "lang": "en", "created_at": "2021-03-25T16:12:35.000Z", "id": "1375118425362628613"}, {"source": "Twitter for iPhone", "public_metrics": {"retweet_count": 11591, "reply_count": 0, "like_count": 0, "quote_count": 0}, "referenced_tweets": [{"type": "retweeted", "id": "1170688657390538752"}], "text": "RT @Fogdo: Thank you @Tesla for this helpful and cool feature :-) https://t.co/FLuY3yFdSL", "author_id": "13298072", "conversation_id": "1374481774714126338", "lang": "en", "created_at": "2021-03-23T22:02:46.000Z", "id": "1374481774714126338"}, {"source": "Twitter for iPhone", "public_metrics": {"retweet_count": 4449, "reply_count": 1492, "like_count": 47613, "quote_count": 543}, "text": "Backseat views from Model Y\n\n\ud83d\udcf8 by loghi007 on Instagram https://t.co/4ss4Hns7fn", "author_id": "13298072", "conversation_id": "1371884988371771399", "lang": "en", "created_at": "2021-03-16T18:04:04.000Z", "id": "1371884988371771399"}, {"source": "Twitter for iPhone", "public_metrics": {"retweet_count": 6309, "reply_count": 1814, "like_count": 79112, "quote_count": 879}, "text": "Semi on the track https://t.co/0QCTYGbLJv", "author_id": "13298072", "conversation_id": "1371125797671538688", "lang": "en", "created_at": "2021-03-14T15:47:19.000Z", "id": "1371125797671538688"}, {"source": "Twitter for iPhone", "public_metrics": {"retweet_count": 1657, "reply_count": 1100, "like_count": 21549, "quote_count": 245}, "text": "Game on \ud83c\udfae\n\n\ud83d\udcf8 by @FromWhereICHG https://t.co/wa4m9gjDMh", "author_id": "13298072", "conversation_id": "1368715658981163008", "lang": "en", "created_at": "2021-03-08T00:10:17.000Z", "id": "1368715658981163008"}, {"source": "Twitter Web App", "public_metrics": {"retweet_count": 11982, "reply_count": 3435, "like_count": 106747, "quote_count": 1875}, "text": "Use Tesla phone app to melt snow &amp; ice off your car before even leaving the house\n\n\ud83d\udcf8 by @cookie_esq https://t.co/P3r8JUOvpv", "author_id": "13298072", "conversation_id": "1366448694111973381", "lang": "en", "created_at": "2021-03-01T18:02:10.000Z", "id": "1366448694111973381"}, {"source": "Twitter for iPhone", "public_metrics": {"retweet_count": 2995, "reply_count": 1553, "like_count": 38348, "quote_count": 230}, "text": "Model 3 earns Top Safety+ award from IIHS for third year in a row https://t.co/rr0QtV20al", "author_id": "13298072", "conversation_id": "1365523849249517568", "lang": "en", "created_at": "2021-02-27T04:47:10.000Z", "id": "1365523849249517568"}, {"source": "Twitter for iPhone", "public_metrics": {"retweet_count": 2383, "reply_count": 0, "like_count": 0, "quote_count": 0}, "referenced_tweets": [{"type": "retweeted", "id": "1363944709501067264"}], "text": "RT @elonmusk: @AustinTeslaClub The Tesla Solar Roof is slightly hydrophobic, so water, snow or ice slide off easily", "author_id": "13298072", "conversation_id": "1363947624785711105", "lang": "en", "created_at": "2021-02-22T20:23:49.000Z", "id": "1363947624785711105"}, {"source": "Twitter for Advertisers (legacy)", "public_metrics": {"retweet_count": 6262, "reply_count": 3350, "like_count": 63987, "quote_count": 532}, "text": "Solar Roof even clears off the snow", "author_id": "13298072", "conversation_id": "1363595197926539268", "lang": "en", "created_at": "2021-02-21T21:03:24.000Z", "id": "1363595197926539268"}, {"source": "Twitter for iPhone", "public_metrics": {"retweet_count": 2023, "reply_count": 1028, "like_count": 27892, "quote_count": 169}, "text": "Plaid winter testing https://t.co/Zau1dWZD2U", "author_id": "13298072", "conversation_id": "1362859869418770432", "lang": "en", "created_at": "2021-02-19T20:21:28.000Z", "id": "1362859869418770432"}, {"source": "Twitter for iPhone", "public_metrics": {"retweet_count": 5461, "reply_count": 2159, "like_count": 59933, "quote_count": 737}, "text": "Two years ago, we launched Dog Mode. Send us your best pics! https://t.co/iXVazZJP3B", "author_id": "13298072", "conversation_id": "1362446840164139009", "lang": "en", "created_at": "2021-02-18T17:00:14.000Z", "id": "1362446840164139009"}, {"source": "Twitter for iPhone", "public_metrics": {"retweet_count": 6689, "reply_count": 4816, "like_count": 134775, "quote_count": 413}, "text": "Winter at Giga Texas https://t.co/eqL8lPICKe", "author_id": "13298072", "conversation_id": "1361704766577991683", "lang": "tl", "created_at": "2021-02-16T15:51:30.000Z", "id": "1361704766577991683"}, {"source": "Twitter for iPhone", "public_metrics": {"retweet_count": 2820, "reply_count": 1143, "like_count": 72848, "quote_count": 196}, "text": "Winter at Giga Berlin https://t.co/ZyUwqWWY7S", "author_id": "13298072", "conversation_id": "1360470410479943684", "lang": "in", "created_at": "2021-02-13T06:06:36.000Z", "id": "1360470410479943684"}, {"source": "Twitter for iPhone", "public_metrics": {"retweet_count": 31172, "reply_count": 0, "like_count": 0, "quote_count": 0}, "referenced_tweets": [{"type": "retweeted", "id": "1359956852520325120"}], "text": "RT @elonmusk: Happy New Year of the Ox! https://t.co/9WFKMYu2oj", "author_id": "13298072", "conversation_id": "1360035166090129408", "lang": "en", "created_at": "2021-02-12T01:17:06.000Z", "id": "1360035166090129408"}, {"source": "Twitter for iPhone", "public_metrics": {"retweet_count": 13637, "reply_count": 0, "like_count": 0, "quote_count": 0}, "referenced_tweets": [{"type": "retweeted", "id": "1356381230925635591"}], "text": "RT @elonmusk: Giga Berlin progress https://t.co/ekpG5qcbUi", "author_id": "13298072", "conversation_id": "1358317056932872193", "lang": "in", "created_at": "2021-02-07T07:29:57.000Z", "id": "1358317056932872193"}, {"source": "Twitter for iPhone", "in_reply_to_user_id": "13298072", "public_metrics": {"retweet_count": 529, "reply_count": 279, "like_count": 9645, "quote_count": 38}, "referenced_tweets": [{"type": "replied_to", "id": "1357503277722718212"}], "text": "It can cast front &amp; rear vehicle underbodies in a single piece each \u2014 down from 70+ parts for same sections previously", "author_id": "13298072", "conversation_id": "1357503277722718212", "lang": "en", "created_at": "2021-02-05T01:36:17.000Z", "id": "1357503279475920897"}, {"source": "Twitter for iPhone", "public_metrics": {"retweet_count": 3207, "reply_count": 841, "like_count": 29978, "quote_count": 530}, "text": "World\u2019s biggest die casting machine https://t.co/MegnFPKQfh", "author_id": "13298072", "conversation_id": "1357503277722718212", "lang": "en", "created_at": "2021-02-05T01:36:17.000Z", "id": "1357503277722718212"}, {"source": "Twitter for iPhone", "public_metrics": {"retweet_count": 835, "reply_count": 518, "like_count": 14812, "quote_count": 141}, "text": "Proud to have scored 100/100 in LGBTQ equality for the 6th year in a row \ud83c\udff3\ufe0f\u200d\ud83c\udf08 https://t.co/zz3PeKRRSL", "author_id": "13298072", "conversation_id": "1356308401790328834", "lang": "en", "created_at": "2021-02-01T18:28:16.000Z", "id": "1356308401790328834"}, {"source": "Twitter for iPhone", "public_metrics": {"retweet_count": 34297, "reply_count": 0, "like_count": 0, "quote_count": 0}, "referenced_tweets": [{"type": "retweeted", "id": "1354618504532684802"}], "text": "RT @elonmusk: Plaid Model S ships next month https://t.co/HFUPTnQiPB", "author_id": "13298072", "conversation_id": "1354752198270464008", "lang": "en", "created_at": "2021-01-28T11:24:28.000Z", "id": "1354752198270464008"}, {"source": "Twitter for iPhone", "in_reply_to_user_id": "13298072", "public_metrics": {"retweet_count": 310, "reply_count": 119, "like_count": 6469, "quote_count": 23}, "referenced_tweets": [{"type": "replied_to", "id": "1354702641008410626"}], "text": "Plaid Model X has the quickest acceleration of any SUV by far, at 2.5 seconds 0-60", "author_id": "13298072", "conversation_id": "1354702639007739905", "lang": "en", "created_at": "2021-01-28T08:07:33.000Z", "id": "1354702642019233795"}, {"source": "Twitter for iPhone", "in_reply_to_user_id": "13298072", "public_metrics": {"retweet_count": 455, "reply_count": 148, "like_count": 7745, "quote_count": 58}, "referenced_tweets": [{"type": "replied_to", "id": "1354702640085676035"}], "text": "Plaid Model S is the first production car to achieve 0-60 in under 2 seconds", "author_id": "13298072", "conversation_id": "1354702639007739905", "lang": "en", "created_at": "2021-01-28T08:07:33.000Z", "id": "1354702641008410626"}, {"source": "Twitter for iPhone", "in_reply_to_user_id": "13298072", "public_metrics": {"retweet_count": 242, "reply_count": 89, "like_count": 3538, "quote_count": 100}, "referenced_tweets": [{"type": "replied_to", "id": "1354702639007739905"}], "text": "You can play The Witcher 3, Cyberpunk &amp; many more", "author_id": "13298072", "conversation_id": "1354702639007739905", "lang": "en", "created_at": "2021-01-28T08:07:33.000Z", "id": "1354702640085676035"}, {"source": "Twitter for iPhone", "public_metrics": {"retweet_count": 2038, "reply_count": 636, "like_count": 19161, "quote_count": 266}, "text": "New Model S &amp; Model X just launched\n\nDetails https://t.co/7Ol1BvJoj8", "author_id": "13298072", "conversation_id": "1354702639007739905", "lang": "en", "created_at": "2021-01-28T08:07:32.000Z", "id": "1354702639007739905"}, {"source": "Twitter for iPhone", "in_reply_to_user_id": "13298072", "public_metrics": {"retweet_count": 934, "reply_count": 320, "like_count": 13575, "quote_count": 112}, "referenced_tweets": [{"type": "replied_to", "id": "1353402390473535488"}], "text": "Also, Model 3 frunks https://t.co/Up848EP3mk", "author_id": "13298072", "conversation_id": "1353402390473535488", "lang": "en", "created_at": "2021-01-24T18:09:57.000Z", "id": "1353404686854807552"}, {"source": "Twitter for iPhone", "public_metrics": {"retweet_count": 3925, "reply_count": 975, "like_count": 47627, "quote_count": 527}, "text": "Stamping Model Y body parts at our Fremont factory https://t.co/qbLrYowJRC", "author_id": "13298072", "conversation_id": "1353402390473535488", "lang": "en", "created_at": "2021-01-24T18:00:49.000Z", "id": "1353402390473535488"}, {"source": "Twitter for iPhone", "public_metrics": {"retweet_count": 2040, "reply_count": 837, "like_count": 35786, "quote_count": 282}, "text": "\u6b22\u8fce! Model Y deliveries in China have officially begun \ud83d\ude98\ud83c\udde8\ud83c\uddf3 https://t.co/fG5aax1k2b", "author_id": "13298072", "conversation_id": "1351186913840009219", "lang": "en", "created_at": "2021-01-18T15:17:18.000Z", "id": "1351186913840009219"}, {"source": "Twitter for iPhone", "public_metrics": {"retweet_count": 4921, "reply_count": 1325, "like_count": 41584, "quote_count": 893}, "text": "Come work on cell / battery production at Giga Texas &amp; Giga Berlin! https://t.co/PhsI5bb0uD https://t.co/jEUatMLDmE", "author_id": "13298072", "conversation_id": "1350912868624035842", "lang": "en", "created_at": "2021-01-17T21:08:21.000Z", "id": "1350912868624035842"}, {"source": "Twitter for iPhone", "public_metrics": {"retweet_count": 1672, "reply_count": 537, "like_count": 15853, "quote_count": 206}, "text": "The best crash is no crash \u2014 with Autopilot enabled, you are 7x less likely to be involved in an accident.\n\nComes standard with every Tesla, at no additional cost. https://t.co/C7no6bBwGc", "author_id": "13298072", "conversation_id": "1349831846247477250", "lang": "en", "created_at": "2021-01-14T21:32:45.000Z", "id": "1349831846247477250"}, {"source": "Twitter Web App", "in_reply_to_user_id": "13298072", "public_metrics": {"retweet_count": 5117, "reply_count": 530, "like_count": 57045, "quote_count": 552}, "referenced_tweets": [{"type": "replied_to", "id": "1349505863237529601"}], "text": "Large crumple zones, rigid body structure &amp; low center of gravity really make a difference https://t.co/Gmwoh7a1gz", "author_id": "13298072", "conversation_id": "1349505863237529601", "lang": "en", "created_at": "2021-01-14T04:23:25.000Z", "id": "1349572805122113540"}, {"source": "Twitter Web App", "public_metrics": {"retweet_count": 2890, "reply_count": 552, "like_count": 44247, "quote_count": 262}, "text": "Model Y awarded 5-star safety rating in every category!\nhttps://t.co/dgbQWofpjf", "author_id": "13298072", "conversation_id": "1349505863237529601", "lang": "en", "created_at": "2021-01-13T23:57:25.000Z", "id": "1349505863237529601"}, {"source": "Twitter Web App", "public_metrics": {"retweet_count": 742, "reply_count": 0, "like_count": 0, "quote_count": 0}, "referenced_tweets": [{"type": "retweeted", "id": "1344339105811935239"}], "text": "RT @TonyChoMrMagic: I just installed the largest (44KW) solar roof in Florida  @teslaenergy @ ChoZen Retreat @livechozen, Thank you @elonmu\u2026", "author_id": "13298072", "conversation_id": "1347944737731346434", "lang": "en", "created_at": "2021-01-09T16:34:03.000Z", "id": "1347944737731346434"}, {"source": "Twitter Web App", "public_metrics": {"retweet_count": 1385, "reply_count": 713, "like_count": 24652, "quote_count": 383}, "text": "The 7-seater option is now available for order on Model Y https://t.co/XLu84G3GJc", "author_id": "13298072", "conversation_id": "1347673670894800898", "lang": "en", "created_at": "2021-01-08T22:36:56.000Z", "id": "1347673670894800898"}, {"source": "Twitter Web App", "public_metrics": {"retweet_count": 1093, "reply_count": 516, "like_count": 11778, "quote_count": 176}, "text": "Model Y Standard Range is now available to order for $41,990\n \n- 244 mile range (EPA est.)\n- Rear-wheel drive\n- 0-60mph in 5.3s\n- Premium interior\n- Autopilot\n- Towing capacity of 3,500 lbs.\n\nhttps://t.co/dU9HoFqQIc", "author_id": "13298072", "conversation_id": "1347673218182643715", "lang": "en", "created_at": "2021-01-08T22:35:08.000Z", "id": "1347673218182643715"}, {"source": "Twitter Web App", "public_metrics": {"retweet_count": 6323, "reply_count": 2325, "like_count": 66147, "quote_count": 1359}, "text": "In 2020, we produced and delivered half a million cars. Huge thanks to all those who made this possible.\nhttps://t.co/q43vz6RMhd", "author_id": "13298072", "conversation_id": "1345377367947005955", "lang": "en", "created_at": "2021-01-02T14:32:15.000Z", "id": "1345377367947005955"}, {"source": "Twitter Web App", "public_metrics": {"retweet_count": 955, "reply_count": 1160, "like_count": 10334, "quote_count": 159}, "text": "Order solar panels before the solar tax credit drops at the end of this year. Pair with Powerwall to experience no more blackouts!\nhttps://t.co/gvX4KnG2ca", "author_id": "13298072", "conversation_id": "1326607188178006016", "lang": "en", "created_at": "2020-11-11T19:26:15.000Z", "id": "1326607188178006016"}, {"source": "Twitter Web App", "public_metrics": {"retweet_count": 3884, "reply_count": 1835, "like_count": 70208, "quote_count": 831}, "text": "20k Superchargers and counting https://t.co/urudyt9Eui", "author_id": "13298072", "conversation_id": "1325493014941216768", "lang": "en", "created_at": "2020-11-08T17:38:55.000Z", "id": "1325493014941216768"}, {"source": "Twitter for Advertisers (legacy)", "public_metrics": {"retweet_count": 2268, "reply_count": 1286, "like_count": 25521, "quote_count": 274}, "text": "There's no place like home..especially if it has a Solar Roof.\n\nThis Kansas ranch got theirs installed in 4 days.", "author_id": "13298072", "conversation_id": "1317251873687113730", "lang": "en", "created_at": "2020-10-16T23:51:34.000Z", "id": "1317251873687113730"}, {"source": "Twitter Web App", "public_metrics": {"retweet_count": 5132, "reply_count": 1145, "like_count": 43972, "quote_count": 844}, "text": "In-car footage from Sunday\u2019s Plaid Model S run at Laguna Seca https://t.co/rwQDBFCWoH", "author_id": "13298072", "conversation_id": "1308618501062422528", "lang": "en", "created_at": "2020-09-23T04:05:38.000Z", "id": "1308618501062422528"}, {"source": "Twitter for Advertisers (legacy)", "public_metrics": {"retweet_count": 2384, "reply_count": 489, "like_count": 19145, "quote_count": 439}, "text": "The only thing beyond Ludicrous is Plaid", "author_id": "13298072", "conversation_id": "1308617112722632704", "lang": "en", "created_at": "2020-09-23T04:00:07.000Z", "id": "1308617112722632704"}, {"source": "Twitter for Advertisers (legacy)", "public_metrics": {"retweet_count": 1808, "reply_count": 443, "like_count": 12998, "quote_count": 237}, "text": "Tesla Battery Day starts now!", "author_id": "13298072", "conversation_id": "1308513116775350272", "lang": "en", "created_at": "2020-09-22T21:06:52.000Z", "id": "1308513116775350272"}, {"source": "Twitter Web App", "public_metrics": {"retweet_count": 682, "reply_count": 330, "like_count": 7606, "quote_count": 33}, "referenced_tweets": [{"type": "quoted", "id": "1293202956939034634"}], "text": "Aka 162 hours of uninterrupted wifi https://t.co/fvm8Y5oERB", "author_id": "13298072", "conversation_id": "1296476645650567169", "lang": "en", "created_at": "2020-08-20T15:58:14.000Z", "id": "1296476645650567169"}, {"source": "Twitter Web App", "public_metrics": {"retweet_count": 1474, "reply_count": 739, "like_count": 17636, "quote_count": 145}, "text": "Big updates in \ud83c\udde8\ud83c\udde6 \n\n\u2013 Trans-Canada Supercharging \u2705 \n\u2013 Model Y deliveries \u2705 \n\u2013 Leasing for Model Y &amp; Model 3 \ud83c\udfaf\nhttps://t.co/gyFBEIsjSP", "author_id": "13298072", "conversation_id": "1295846581258686464", "lang": "en", "created_at": "2020-08-18T22:14:35.000Z", "id": "1295846581258686464"}, {"source": "Twitter for iPhone", "public_metrics": {"retweet_count": 203, "reply_count": 0, "like_count": 0, "quote_count": 0}, "referenced_tweets": [{"type": "retweeted", "id": "1293991666668511232"}], "text": "RT @UndecidedMF: In Tesla\u2019s Q2 earnings call they dropped the little bombshell that Tesla's solar panels cost $1.49 per watt after incentiv\u2026", "author_id": "13298072", "conversation_id": "1294309164257120261", "lang": "en", "created_at": "2020-08-14T16:25:26.000Z", "id": "1294309164257120261"}, {"source": "Twitter Web App", "public_metrics": {"retweet_count": 1883, "reply_count": 529, "like_count": 21105, "quote_count": 210}, "text": "Live roof &gt; Dead roof https://t.co/scCQ1UXUJb", "author_id": "13298072", "conversation_id": "1291831728009441280", "lang": "en", "created_at": "2020-08-07T20:20:59.000Z", "id": "1291831728009441280"}, {"source": "Twitter Web App", "public_metrics": {"retweet_count": 4906, "reply_count": 1361, "like_count": 53197, "quote_count": 694}, "text": "Looking up in Model Y https://t.co/iAfpJ491Zz", "author_id": "13298072", "conversation_id": "1291176823557099520", "lang": "en", "created_at": "2020-08-06T00:58:38.000Z", "id": "1291176823557099520"}, {"source": "Twitter for iPhone", "public_metrics": {"retweet_count": 1081, "reply_count": 432, "like_count": 12946, "quote_count": 97}, "text": "Tesla Q2 Vehicle Safety Report https://t.co/C7no6bBwGc", "author_id": "13298072", "conversation_id": "1289406715667111936", "lang": "es", "created_at": "2020-08-01T03:44:51.000Z", "id": "1289406715667111936"}, {"source": "Twitter Web App", "public_metrics": {"retweet_count": 2455, "reply_count": 1030, "like_count": 30826, "quote_count": 268}, "text": "https://t.co/jmkacbRb5D", "author_id": "13298072", "conversation_id": "1286057855422881792", "lang": "und", "created_at": "2020-07-22T21:57:41.000Z", "id": "1286057855422881792"}, {"source": "Twitter for iPhone", "public_metrics": {"retweet_count": 1534, "reply_count": 724, "like_count": 16471, "quote_count": 159}, "text": "Tesla Q2 2020 Vehicle Production &amp; Deliveries | Tesla, Inc. https://t.co/hgJDXLWmBg", "author_id": "13298072", "conversation_id": "1278757900568023041", "lang": "ca", "created_at": "2020-07-02T18:30:16.000Z", "id": "1278757900568023041"}, {"source": "Twitter for iPhone", "public_metrics": {"retweet_count": 2184, "reply_count": 703, "like_count": 20978, "quote_count": 204}, "text": "https://t.co/26o1bAP14v", "author_id": "13298072", "conversation_id": "1274443110362214405", "lang": "und", "created_at": "2020-06-20T20:44:50.000Z", "id": "1274443110362214405"}, {"source": "Twitter for iPhone", "public_metrics": {"retweet_count": 1506, "reply_count": 483, "like_count": 15511, "quote_count": 133}, "text": "https://t.co/MROOCn4w9f", "author_id": "13298072", "conversation_id": "1270173874844397569", "lang": "und", "created_at": "2020-06-09T02:00:25.000Z", "id": "1270173874844397569"}, {"source": "Twitter for iPhone", "public_metrics": {"retweet_count": 3343, "reply_count": 2004, "like_count": 42896, "quote_count": 580}, "text": "https://t.co/X9dzVXLBLx", "author_id": "13298072", "conversation_id": "1259307919721459712", "lang": "und", "created_at": "2020-05-10T02:22:59.000Z", "id": "1259307919721459712"}, {"source": "Twitter Web App", "public_metrics": {"retweet_count": 3067, "reply_count": 914, "like_count": 33154, "quote_count": 286}, "text": "Tesla wins 5/6 Kelley Blue Book awards\n\n\ud83c\udfc6 Best Overall\n\ud83c\udfc6 Best Value\n\ud83c\udfc6 Most Refined\n\ud83c\udfc6 Best Performance\n\ud83c\udfc6 Best Styling", "author_id": "13298072", "conversation_id": "1248048276714094592", "lang": "en", "created_at": "2020-04-09T00:41:11.000Z", "id": "1248048276714094592"}, {"source": "Twitter for Advertisers (legacy)", "public_metrics": {"retweet_count": 8061, "reply_count": 1509, "like_count": 39014, "quote_count": 1493}, "text": "Engineering update on the Tesla ventilator", "author_id": "13298072", "conversation_id": "1246940326838718464", "lang": "en", "created_at": "2020-04-05T23:18:35.000Z", "id": "1246940326838718464"}, {"source": "Twitter for iPhone", "in_reply_to_user_id": "26982121", "public_metrics": {"retweet_count": 184, "reply_count": 62, "like_count": 1409, "quote_count": 32}, "referenced_tweets": [{"type": "replied_to", "id": "1241813089336446976"}], "text": "@UCLAHealth @elonmusk @3M Glad we can help! We\u2019re sending masks and supplies to as many hospitals as we can.", "author_id": "13298072", "conversation_id": "1241813089336446976", "lang": "en", "created_at": "2020-03-22T20:30:51.000Z", "id": "1241824684586352640"}, {"source": "Twitter Web App", "public_metrics": {"retweet_count": 5376, "reply_count": 1235, "like_count": 39337, "quote_count": 780}, "text": "Model Y deliveries begin!\n\nhttps://t.co/ZhuiM5MTOf https://t.co/3gX6MBPmhp", "author_id": "13298072", "conversation_id": "1239607579518484480", "lang": "en", "created_at": "2020-03-16T17:40:52.000Z", "id": "1239607579518484480"}, {"source": "Twitter Web App", "public_metrics": {"retweet_count": 1207, "reply_count": 279, "like_count": 20219, "quote_count": 145}, "text": "Giga New York built 4MW of Solar Roof last week, enough for up to 1000 homes!", "author_id": "13298072", "conversation_id": "1239021421264691200", "lang": "en", "created_at": "2020-03-15T02:51:41.000Z", "id": "1239021421264691200"}, {"source": "Twitter for Advertisers (legacy)", "public_metrics": {"retweet_count": 795, "reply_count": 213, "like_count": 7881, "quote_count": 89}, "text": "Track Mode V2 for Model 3 Performance introduces more advanced handling customization and lap data recording.", "author_id": "13298072", "conversation_id": "1237395237099556864", "lang": "en", "created_at": "2020-03-10T15:09:48.000Z", "id": "1237395237099556864"}, {"source": "Twitter for Advertisers (legacy)", "public_metrics": {"retweet_count": 3694, "reply_count": 969, "like_count": 48213, "quote_count": 380}, "text": "Art of the Roof", "author_id": "13298072", "conversation_id": "1235662616695107587", "lang": "en", "created_at": "2020-03-05T20:24:59.000Z", "id": "1235662616695107587"}, {"source": "Twitter for Advertisers (legacy)", "public_metrics": {"retweet_count": 1828, "reply_count": 539, "like_count": 17578, "quote_count": 153}, "text": "Model 3 recently earned the 2020 IIHS Top Safety Pick+ Award. Winning cars are selected on their ability to protect people inside and outside the car \n\ud83d\udc4d\ud83c\udffb\ud83d\ude98", "author_id": "13298072", "conversation_id": "1235278941494980608", "lang": "en", "created_at": "2020-03-04T19:00:24.000Z", "id": "1235278941494980608"}, {"source": "Twitter Web App", "public_metrics": {"retweet_count": 3959, "reply_count": 746, "like_count": 28972, "quote_count": 416}, "text": "Solar Roof is taking off across the US. Become a Solar Roof installer today, no experience needed!\n\nhttps://t.co/qX1lEPlkNQ https://t.co/EQKWaoSiqH", "author_id": "13298072", "conversation_id": "1228852344265179136", "lang": "en", "created_at": "2020-02-16T01:23:24.000Z", "id": "1228852344265179136"}, {"source": "Twitter Web App", "public_metrics": {"retweet_count": 4034, "reply_count": 960, "like_count": 37719, "quote_count": 749}, "text": "Roofs never looked so good https://t.co/kC0NQAuklW https://t.co/tPW7rJtNHQ", "author_id": "13298072", "conversation_id": "1226628461277483008", "lang": "en", "created_at": "2020-02-09T22:06:29.000Z", "id": "1226628461277483008"}, {"source": "Twitter Web App", "public_metrics": {"retweet_count": 2224, "reply_count": 670, "like_count": 15964, "quote_count": 312}, "text": "There is no \"unintended acceleration\" in Tesla vehicles\n\nhttps://t.co/BcYrcX03A4", "author_id": "13298072", "conversation_id": "1219356237176795136", "lang": "en", "created_at": "2020-01-20T20:29:16.000Z", "id": "1219356237176795136"}, {"source": "Twitter Web App", "public_metrics": {"retweet_count": 2181, "reply_count": 513, "like_count": 19284, "quote_count": 299}, "text": "We just delivered our first customer cars from Gigafactory Shanghai, marking only one year from when the teams broke ground on the site. https://t.co/UfUxEyRQv0", "author_id": "13298072", "conversation_id": "1214488420770181121", "lang": "en", "created_at": "2020-01-07T10:06:18.000Z", "id": "1214488420770181121"}, {"source": "Twitter Web App", "public_metrics": {"retweet_count": 1384, "reply_count": 374, "like_count": 16325, "quote_count": 87}, "referenced_tweets": [{"type": "quoted", "id": "1211476694382440451"}], "text": "What a way to close out 2019, and this is only just the beginning. \nCongratulations to the Shanghai team! https://t.co/N6U8qlTPWp", "author_id": "13298072", "conversation_id": "1211489609978437632", "lang": "en", "created_at": "2019-12-30T03:30:06.000Z", "id": "1211489609978437632"}, {"source": "Twitter Web App", "public_metrics": {"retweet_count": 2036, "reply_count": 702, "like_count": 22134, "quote_count": 204}, "referenced_tweets": [{"type": "quoted", "id": "1208546631328632832"}], "text": "Trans-Canada Supercharger route from Vancouver to Halifax is now open! \ud83c\udde8\ud83c\udde6\u26a1\nOver half the locations are V3 for the fastest charging speeds. https://t.co/42mnW3hNL5", "author_id": "13298072", "conversation_id": "1209532295813554176", "lang": "en", "created_at": "2019-12-24T17:52:26.000Z", "id": "1209532295813554176"}, {"source": "Twitter Web App", "public_metrics": {"retweet_count": 616, "reply_count": 306, "like_count": 8772, "quote_count": 77}, "referenced_tweets": [{"type": "quoted", "id": "1201630240101085186"}], "text": "Money printers for all https://t.co/wYCAzV25e3", "author_id": "13298072", "conversation_id": "1205693814024753153", "lang": "en", "created_at": "2019-12-14T03:39:40.000Z", "id": "1205693814024753153"}, {"source": "Twitter Web App", "public_metrics": {"retweet_count": 750, "reply_count": 215, "like_count": 10354, "quote_count": 51}, "text": "Enjoy charging your car with the sun https://t.co/vMTE5aE8uY", "author_id": "13298072", "conversation_id": "1205279119551815680", "lang": "en", "created_at": "2019-12-13T00:11:49.000Z", "id": "1205279119551815680"}, {"source": "Twitter Web App", "public_metrics": {"retweet_count": 1315, "reply_count": 541, "like_count": 16979, "quote_count": 139}, "text": "Just in case you make your roofing decisions based on slo mo videos https://t.co/6bggrC7yxu", "author_id": "13298072", "conversation_id": "1203082344602591232", "lang": "en", "created_at": "2019-12-06T22:42:37.000Z", "id": "1203082344602591232"}, {"source": "Twitter for Advertisers (legacy)", "public_metrics": {"retweet_count": 2352, "reply_count": 581, "like_count": 23105, "quote_count": 182}, "text": "Model X just earned 5 stars from Euro NCAP in safety testing", "author_id": "13298072", "conversation_id": "1202279527839191040", "lang": "en", "created_at": "2019-12-04T17:32:31.000Z", "id": "1202279527839191040"}, {"source": "Twitter Web App", "public_metrics": {"retweet_count": 6467, "reply_count": 1743, "like_count": 53958, "quote_count": 1100}, "text": "I'm gonna tell my kids this is the first pick-up https://t.co/RyNcYfIZ33", "author_id": "13298072", "conversation_id": "1198343931005505536", "lang": "en", "created_at": "2019-11-23T20:53:51.000Z", "id": "1198343931005505536"}, {"source": "Twitter for iPhone", "public_metrics": {"retweet_count": 2892, "reply_count": 0, "like_count": 0, "quote_count": 0}, "referenced_tweets": [{"type": "retweeted", "id": "1197732160137940992"}], "text": "RT @MotorTrend: The MotorTrend team visited @Tesla twice during the development of #Cybertruck. Six exclusive stories and five videos at ht\u2026", "author_id": "13298072", "conversation_id": "1197967929750327296", "lang": "en", "created_at": "2019-11-22T19:59:46.000Z", "id": "1197967929750327296"}, {"source": "Twitter Web App", "public_metrics": {"retweet_count": 2961, "reply_count": 1376, "like_count": 26927, "quote_count": 939}, "text": "More utility than a pick-up\nBetter performance than a sports car\n\nhttps://t.co/28RWdWLYMi", "author_id": "13298072", "conversation_id": "1197952164565372929", "lang": "en", "created_at": "2019-11-22T18:57:07.000Z", "id": "1197952164565372929"}, {"source": "Twitter Web App", "public_metrics": {"retweet_count": 2677, "reply_count": 1071, "like_count": 25454, "quote_count": 434}, "text": "Cybertruck Unveil livestream starts at 8pm \nhttps://t.co/BhTBgNqeWQ https://t.co/qzKnsIkkms", "author_id": "13298072", "conversation_id": "1197697924429271040", "lang": "en", "created_at": "2019-11-22T02:06:51.000Z", "id": "1197697924429271040"}, {"source": "Twitter Web App", "public_metrics": {"retweet_count": 7339, "reply_count": 1592, "like_count": 48826, "quote_count": 842}, "text": "Cybertruck Unveil starts at 8\n\nStay tuned for livestream https://t.co/zrbsoKKLd7", "author_id": "13298072", "conversation_id": "1197612306705707013", "lang": "en", "created_at": "2019-11-21T20:26:39.000Z", "id": "1197612306705707013"}, {"source": "Twitter Web App", "in_reply_to_user_id": "979225070764634112", "public_metrics": {"retweet_count": 41, "reply_count": 57, "like_count": 1138, "quote_count": 6}, "referenced_tweets": [{"type": "replied_to", "id": "1194708917932003328"}], "text": "@tesletter Weekly screen time report got too high", "author_id": "13298072", "conversation_id": "1194708409251069952", "lang": "en", "created_at": "2019-11-13T23:08:01.000Z", "id": "1194753812768026624"}, {"source": "Twitter Web App", "public_metrics": {"retweet_count": 1791, "reply_count": 407, "like_count": 24933, "quote_count": 98}, "text": "We were very honored to accept one of Europe's most prestigious awards yesterday, Das Goldene Lenkrad (the Golden Steering Wheel), with Model 3 scoring the highest of all tested cars \ud83c\udfc6", "author_id": "13298072", "conversation_id": "1194708409251069952", "lang": "en", "created_at": "2019-11-13T20:07:36.000Z", "id": "1194708409251069952"}, {"source": "TweetDeck", "public_metrics": {"retweet_count": 1537, "reply_count": 376, "like_count": 11798, "quote_count": 173}, "text": "Solar Roof uses durable glass solar tiles to generate electricity.\n\u00a0\nOur latest version only takes a few days to set up and is comparable to the cost of a composition shingle roof + electrical bill.\n\u00a0\nInstallations begin next month.\nhttps://t.co/27tB768e9e", "author_id": "13298072", "conversation_id": "1187874934653100032", "lang": "en", "created_at": "2019-10-25T23:33:48.000Z", "id": "1187874934653100032"}, {"source": "Twitter for Advertisers (legacy)", "public_metrics": {"retweet_count": 593, "reply_count": 731, "like_count": 8542, "quote_count": 49}, "text": "Submit questions for our Solar Roof Q&amp;A ahead of our 2pm launch:", "author_id": "13298072", "conversation_id": "1187798782198595589", "lang": "en", "created_at": "2019-10-25T18:31:12.000Z", "id": "1187798782198595589"}, {"source": "TweetDeck", "public_metrics": {"retweet_count": 387, "reply_count": 116, "like_count": 3092, "quote_count": 37}, "text": "Join us at 2pm PT today to learn all about our V3 Solar Roof product. \n\nVisit https://t.co/rd0ILdpzRL to listen in.", "author_id": "13298072", "conversation_id": "1187768486300438528", "lang": "en", "created_at": "2019-10-25T16:30:49.000Z", "id": "1187768486300438528"}, {"source": "TweetDeck", "public_metrics": {"retweet_count": 311, "reply_count": 190, "like_count": 3935, "quote_count": 27}, "referenced_tweets": [{"type": "quoted", "id": "1184232118223822848"}], "text": "One of us, One of us.\n\nBecome a Production Associate: https://t.co/eatwqqWhdC https://t.co/fr3JuYnVb0", "author_id": "13298072", "conversation_id": "1184896539795308544", "lang": "en", "created_at": "2019-10-17T18:18:44.000Z", "id": "1184896539795308544"}, {"source": "TweetDeck", "in_reply_to_user_id": "58765620", "public_metrics": {"retweet_count": 14, "reply_count": 15, "like_count": 199, "quote_count": 0}, "referenced_tweets": [{"type": "replied_to", "id": "1184562257612677123"}], "text": "@WilliamLaitinen @elonmusk Spookercharger", "author_id": "13298072", "conversation_id": "1184562257612677123", "lang": "en", "created_at": "2019-10-16T20:12:43.000Z", "id": "1184562837961789441"}, {"source": "TweetDeck", "public_metrics": {"retweet_count": 257, "reply_count": 114, "like_count": 5812, "quote_count": 15}, "referenced_tweets": [{"type": "quoted", "id": "1184202345170817024"}], "text": "yesterday we almost tweeted that we have a great rash lab instead of crash lab and we all had a good laugh as we all had a good scratch https://t.co/10oLEtnuM4", "author_id": "13298072", "conversation_id": "1184479086724427777", "lang": "en", "created_at": "2019-10-16T14:39:55.000Z", "id": "1184479086724427777"}, {"source": "Twitter Web App", "in_reply_to_user_id": "2735039144", "public_metrics": {"retweet_count": 21, "reply_count": 10, "like_count": 300, "quote_count": 2}, "referenced_tweets": [{"type": "replied_to", "id": "1176267570053373952"}], "text": "@Tyl3rjam3s don't", "author_id": "13298072", "conversation_id": "1176267570053373952", "lang": "en", "created_at": "2019-10-16T14:13:32.000Z", "id": "1184472448726470657"}, {"source": "Twitter Web App", "in_reply_to_user_id": "727955767567884289", "public_metrics": {"retweet_count": 22, "reply_count": 17, "like_count": 532, "quote_count": 2}, "referenced_tweets": [{"type": "replied_to", "id": "1184202435016851457"}], "text": "@HarryStoltz1 F", "author_id": "13298072", "conversation_id": "1184202345170817024", "lang": "und", "created_at": "2019-10-15T20:32:17.000Z", "id": "1184205373449879552"}, {"source": "Twitter Web App", "public_metrics": {"retweet_count": 843, "reply_count": 230, "like_count": 10375, "quote_count": 73}, "text": "Do you want a sneak peek of our crash lab?\n\nOf course you do. \n\nIt\u2019s one of the reasons why Model 3 is among the safest cars on the road.\nhttps://t.co/jQxWizz0ea", "author_id": "13298072", "conversation_id": "1184202345170817024", "lang": "en", "created_at": "2019-10-15T20:20:15.000Z", "id": "1184202345170817024"}, {"source": "Twitter Web App", "public_metrics": {"retweet_count": 2230, "reply_count": 0, "like_count": 0, "quote_count": 0}, "referenced_tweets": [{"type": "retweeted", "id": "1182812717083611138"}], "text": "RT @elonmusk: Get Tesla Solar plus Powerwall battery for 24/7 clean power &amp; no more blackouts! https://t.co/mDoPO17YB9", "author_id": "13298072", "conversation_id": "1183780121238560768", "lang": "en", "created_at": "2019-10-14T16:22:29.000Z", "id": "1183780121238560768"}, {"source": "Twitter Web App", "in_reply_to_user_id": "718894876956475392", "public_metrics": {"retweet_count": 6, "reply_count": 8, "like_count": 99, "quote_count": 2}, "referenced_tweets": [{"type": "replied_to", "id": "1181978455895920642"}], "text": "@Super_modi_ we're good", "author_id": "13298072", "conversation_id": "1181977669556211712", "lang": "en", "created_at": "2019-10-09T17:11:45.000Z", "id": "1181980583070748672"}, {"source": "Twitter Web App", "in_reply_to_user_id": "13298072", "public_metrics": {"retweet_count": 34, "reply_count": 34, "like_count": 1316, "quote_count": 1}, "referenced_tweets": [{"type": "replied_to", "id": "1181977978496049152"}], "text": "@Super_modi_ CAR", "author_id": "13298072", "conversation_id": "1181977669556211712", "lang": "und", "created_at": "2019-10-09T17:01:36.000Z", "id": "1181978026344697856"}, {"source": "Twitter Web App", "in_reply_to_user_id": "718894876956475392", "public_metrics": {"retweet_count": 50, "reply_count": 21, "like_count": 1646, "quote_count": 3}, "referenced_tweets": [{"type": "replied_to", "id": "1181977808588939265"}], "text": "@Super_modi_ CAR-aoke guys", "author_id": "13298072", "conversation_id": "1181977669556211712", "lang": "en", "created_at": "2019-10-09T17:01:24.000Z", "id": "1181977978496049152"}, {"source": "Twitter Web App", "public_metrics": {"retweet_count": 1249, "reply_count": 316, "like_count": 21330, "quote_count": 127}, "text": "Caraoke is all fun and games until you alienate your children by knowing every single word to Let It Go.", "author_id": "13298072", "conversation_id": "1181977669556211712", "lang": "en", "created_at": "2019-10-09T17:00:11.000Z", "id": "1181977669556211712"}], "meta": {"oldest_id": "1181977669556211712", "newest_id": "1391073650971926532", "result_count": 100, "next_token": "7140dibdnow9c7btw3q4tae85ik135cw818hh87wcknqq"}}